{"generated_at":"2026-07-22T10:56:55.168Z","city":"atl","source":"OpenStreetMap","count":878,"eats":[{"name":"Raging Burrito","lat":33.77447,"lng":-84.29553,"kind":"restaurant","cuisine":"latin american"},{"name":"Dumpling Master","lat":33.78963,"lng":-84.30708,"kind":"restaurant","cuisine":"asian"},{"name":"Bread Coffeehouse","lat":33.78835,"lng":-84.3207,"kind":"cafe","cuisine":"coffee shop"},{"name":"Brake Pad","lat":33.66284,"lng":-84.44662,"kind":"restaurant","cuisine":"burger"},{"name":"The Vortex Bar & Grill","lat":33.77903,"lng":-84.38446,"kind":"restaurant","cuisine":"burger"},{"name":"Inman Perk Coffee","lat":33.76252,"lng":-84.35914,"kind":"cafe","cuisine":"coffee shop"},{"name":"Ruth's Chris","lat":33.76077,"lng":-84.39426,"kind":"restaurant","cuisine":"steak house"},{"name":"Ray's in the City","lat":33.76039,"lng":-84.38773,"kind":"restaurant","cuisine":"seafood"},{"name":"The Drafting Table Cocktails and Kitchen","lat":33.76026,"lng":-84.38799,"kind":"restaurant","cuisine":"american"},{"name":"The Majestic Diner","lat":33.77364,"lng":-84.35372,"kind":"restaurant","cuisine":"american"},{"name":"Ted's Montana Grill","lat":33.75856,"lng":-84.39065,"kind":"restaurant","cuisine":"american"},{"name":"Ray's NY Pizza, Cedar's Mediterranean","lat":33.77665,"lng":-84.3881,"kind":"restaurant","cuisine":"pizza"},{"name":"Boho Taco","lat":33.77665,"lng":-84.3879,"kind":"restaurant","cuisine":"mexican"},{"name":"Asian Fusion","lat":33.77702,"lng":-84.38926,"kind":"restaurant","cuisine":"asian"},{"name":"Gyro Bros","lat":33.77701,"lng":-84.3901,"kind":"restaurant","cuisine":"greek"},{"name":"Sankranti Indian Kitchen","lat":33.77702,"lng":-84.39026,"kind":"restaurant","cuisine":"indian"},{"name":"La Fonda Latina","lat":33.77351,"lng":-84.35713,"kind":"restaurant","cuisine":"mexican"},{"name":"El Ponce","lat":33.77355,"lng":-84.35665,"kind":"restaurant","cuisine":"mexican"},{"name":"Siam Thai","lat":33.77446,"lng":-84.29588,"kind":"restaurant","cuisine":"thai"},{"name":"The Iberian Pig","lat":33.77446,"lng":-84.29601,"kind":"restaurant","cuisine":"spanish"},{"name":"Rebel Teahouse","lat":33.77545,"lng":-84.29422,"kind":"cafe","cuisine":"bubble tea"},{"name":"Cafe Alsace","lat":33.77546,"lng":-84.29548,"kind":"restaurant","cuisine":"french"},{"name":"Victory Sandwich Bar","lat":33.77421,"lng":-84.29502,"kind":"restaurant","cuisine":"sandwich"},{"name":"Mojo Pizza N Pub","lat":33.75934,"lng":-84.30351,"kind":"restaurant","cuisine":"pizza"},{"name":"Green Ginger","lat":33.77668,"lng":-84.29969,"kind":"restaurant","cuisine":"asian"},{"name":"FolkArt","lat":33.77541,"lng":-84.29807,"kind":"restaurant","cuisine":"breakfast"},{"name":"Noodle","lat":33.77536,"lng":-84.29459,"kind":"restaurant","cuisine":"noodle"},{"name":"Ford's BBQ","lat":33.76047,"lng":-84.3035,"kind":"restaurant","cuisine":"barbecue"},{"name":"Paolino Italian Restaurant","lat":33.76058,"lng":-84.30313,"kind":"restaurant","cuisine":"pasta"},{"name":"Out of the Pan","lat":33.7759,"lng":-84.29638,"kind":"cafe","cuisine":"american"},{"name":"Adryannis","lat":33.77648,"lng":-84.29599,"kind":"restaurant","cuisine":"greek"},{"name":"Mellow Mushroom","lat":33.77543,"lng":-84.30094,"kind":"restaurant","cuisine":"pizza"},{"name":"Cafe Lily","lat":33.77536,"lng":-84.30023,"kind":"restaurant","cuisine":"mediterranean"},{"name":"Sushi Avenue","lat":33.77521,"lng":-84.30022,"kind":"restaurant","cuisine":"sushi"},{"name":"Sapori di Napoli","lat":33.77344,"lng":-84.2951,"kind":"restaurant","cuisine":"italian"},{"name":"Doc Chey's Noodle House","lat":33.7932,"lng":-84.35188,"kind":"restaurant","cuisine":"noodle"},{"name":"Pomodoro","lat":33.79263,"lng":-84.35235,"kind":"restaurant","cuisine":"italian"},{"name":"Rosebud","lat":33.79247,"lng":-84.35213,"kind":"restaurant","cuisine":"american"},{"name":"Burnt Fork BBQ","lat":33.7782,"lng":-84.29512,"kind":"restaurant","cuisine":"barbecue"},{"name":"La Fonda Latina","lat":33.76476,"lng":-84.3338,"kind":"restaurant","cuisine":"mexican"},{"name":"Pizza Hut","lat":33.65866,"lng":-84.41791,"kind":"restaurant","cuisine":"pizza"},{"name":"Pit Boss BBQ","lat":33.65816,"lng":-84.41644,"kind":"restaurant","cuisine":"barbecue"},{"name":"Bone Garden Cantina","lat":33.79357,"lng":-84.42595,"kind":"restaurant","cuisine":"mexican"},{"name":"Starbucks","lat":33.85719,"lng":-84.34364,"kind":"cafe","cuisine":"coffee shop"},{"name":"Starbucks","lat":33.81881,"lng":-84.38836,"kind":"cafe","cuisine":"coffee shop"},{"name":"Caribou Coffee","lat":33.84394,"lng":-84.37015,"kind":"cafe","cuisine":"coffee shop"},{"name":"Waffle House","lat":33.77668,"lng":-84.38944,"kind":"restaurant","cuisine":"american"},{"name":"Doc Chey's Dragon Bowl","lat":33.78816,"lng":-84.32662,"kind":"restaurant","cuisine":"noodle"},{"name":"The Vortex Bar & Grill","lat":33.76626,"lng":-84.34921,"kind":"restaurant","cuisine":"burger"},{"name":"Woody's Famous Philadelphia Cheesesteaks","lat":33.78096,"lng":-84.36874,"kind":"restaurant","cuisine":"sandwich"},{"name":"Thai Diner","lat":33.8722,"lng":-84.45806,"kind":"restaurant","cuisine":"thai"},{"name":"Sear","lat":33.76133,"lng":-84.38482,"kind":"restaurant","cuisine":"american"},{"name":"Starbucks","lat":33.75845,"lng":-84.39708,"kind":"cafe","cuisine":"coffee shop"},{"name":"American Deli","lat":33.77544,"lng":-84.29446,"kind":"restaurant","cuisine":"sandwich"},{"name":"Rev Coffee Roasters","lat":33.88215,"lng":-84.50421,"kind":"cafe","cuisine":"coffee shop"},{"name":"Waffle House","lat":33.87258,"lng":-84.52893,"kind":"restaurant","cuisine":"american"},{"name":"Botica","lat":33.80531,"lng":-84.39417,"kind":"restaurant","cuisine":"mexican"},{"name":"Blaze Pizza","lat":33.78995,"lng":-84.30586,"kind":"restaurant","cuisine":"pizza"},{"name":"Savage Pizza","lat":33.76724,"lng":-84.34937,"kind":"restaurant","cuisine":"pizza"},{"name":"Urban Pie","lat":33.75133,"lng":-84.32187,"kind":"restaurant","cuisine":"pizza"},{"name":"Mangos Caribbean","lat":33.75569,"lng":-84.38178,"kind":"restaurant","cuisine":"caribbean"},{"name":"Holy Taco","lat":33.74031,"lng":-84.34463,"kind":"restaurant","cuisine":"mexican"},{"name":"Marlee's Coffee and Tea","lat":33.74972,"lng":-84.37871,"kind":"cafe","cuisine":"coffee shop"},{"name":"Starbucks","lat":33.76807,"lng":-84.34945,"kind":"cafe","cuisine":"coffee shop"},{"name":"Luna Nueva","lat":33.76511,"lng":-84.3498,"kind":"restaurant","cuisine":"mexican"},{"name":"Niramish","lat":33.76489,"lng":-84.35005,"kind":"restaurant","cuisine":"indian"},{"name":"Sweet Lime","lat":33.76459,"lng":-84.35051,"kind":"restaurant","cuisine":"thai"},{"name":"El Bandito Mexican Grill","lat":33.76328,"lng":-84.35153,"kind":"restaurant","cuisine":"mexican"},{"name":"Elmyr","lat":33.76357,"lng":-84.35131,"kind":"restaurant","cuisine":"burrito"},{"name":"Ali Baba Mediterranean","lat":33.7638,"lng":-84.35103,"kind":"restaurant","cuisine":"turkish"},{"name":"Starbucks","lat":33.82559,"lng":-84.36561,"kind":"cafe","cuisine":"coffee shop"},{"name":"Treehouse Restaurant and Pub","lat":33.81878,"lng":-84.38119,"kind":"restaurant","cuisine":"american"},{"name":"Paul's Restaurant","lat":33.81796,"lng":-84.3812,"kind":"restaurant","cuisine":"regional"},{"name":"EAV Thai & Sushi","lat":33.74116,"lng":-84.34668,"kind":"restaurant","cuisine":"sushi"},{"name":"KPot Korean BBQ & Hot Pot","lat":33.80241,"lng":-84.41275,"kind":"restaurant","cuisine":"korean"},{"name":"Yoi Yoi Japanese Steakhouse & Sushi","lat":33.8103,"lng":-84.41605,"kind":"restaurant","cuisine":"japanese"},{"name":"Pero's Pizza & Pasta","lat":33.85091,"lng":-84.42916,"kind":"restaurant","cuisine":"pizza"},{"name":"Apres Diem","lat":33.77918,"lng":-84.36716,"kind":"restaurant","cuisine":"european"},{"name":"Umma Kitchen","lat":33.78038,"lng":-84.3687,"kind":"restaurant","cuisine":"korean"},{"name":"Rosso Red Sauce Joint","lat":33.78026,"lng":-84.36805,"kind":"restaurant","cuisine":"italian"},{"name":"Mellow Mushroom","lat":33.78029,"lng":-84.36852,"kind":"restaurant","cuisine":"pizza"},{"name":"Farm Burger","lat":33.78212,"lng":-84.35388,"kind":"restaurant","cuisine":"burger"},{"name":"La Tavola","lat":33.78245,"lng":-84.35491,"kind":"restaurant","cuisine":"italian"},{"name":"Fox Bros. Bar-B-Q","lat":33.761,"lng":-84.34742,"kind":"restaurant","cuisine":"barbecue"},{"name":"Home Bar","lat":33.75139,"lng":-84.32244,"kind":"restaurant","cuisine":"american"},{"name":"The Argonaut","lat":33.75164,"lng":-84.32337,"kind":"restaurant","cuisine":"seafood"},{"name":"Landmark Diner - Downtown","lat":33.75661,"lng":-84.38909,"kind":"cafe","cuisine":"burger"},{"name":"No Mas Cantina","lat":33.74976,"lng":-84.40088,"kind":"restaurant","cuisine":"mexican"},{"name":"J.R. Cricket's","lat":33.77104,"lng":-84.38318,"kind":"restaurant","cuisine":"american"},{"name":"Benihana","lat":33.81279,"lng":-84.3916,"kind":"restaurant","cuisine":"japanese"},{"name":"Wave 3 Coffee","lat":33.83988,"lng":-84.37712,"kind":"cafe","cuisine":"coffee shop"},{"name":"Waffle House","lat":33.86114,"lng":-84.33901,"kind":"restaurant","cuisine":"american"},{"name":"El Potro","lat":33.84524,"lng":-84.32673,"kind":"restaurant","cuisine":"mexican"},{"name":"Pizza Hut","lat":33.84205,"lng":-84.32897,"kind":"restaurant","cuisine":"pizza"},{"name":"Pancho's Mexican Restaurant & Cantina","lat":33.82628,"lng":-84.34801,"kind":"restaurant","cuisine":"mexican"},{"name":"Starbucks","lat":33.81858,"lng":-84.31252,"kind":"cafe","cuisine":"coffee shop"},{"name":"Willy's Mexican Grill","lat":33.78392,"lng":-84.37874,"kind":"restaurant","cuisine":"mexican"},{"name":"Grant Central Pizza East","lat":33.74003,"lng":-84.34568,"kind":"restaurant","cuisine":"pizza"},{"name":"Joe's East Atlanta Coffee Shop","lat":33.74035,"lng":-84.34543,"kind":"cafe","cuisine":"coffee shop"},{"name":"Gekko Sushi and Lounge","lat":33.77131,"lng":-84.36787,"kind":"restaurant","cuisine":"sushi"},{"name":"Big Boss Chinese","lat":33.78128,"lng":-84.39012,"kind":"restaurant","cuisine":"chinese"},{"name":"Ziba's","lat":33.73923,"lng":-84.368,"kind":"restaurant","cuisine":"american"},{"name":"Matador Cantina","lat":33.74045,"lng":-84.35764,"kind":"restaurant","cuisine":"mexican"},{"name":"Vickery's","lat":33.74045,"lng":-84.3574,"kind":"restaurant","cuisine":"american"},{"name":"Revolution Doughnuts","lat":33.76546,"lng":-84.30831,"kind":"cafe","cuisine":"donut"},{"name":"Yogli Mogli","lat":33.78857,"lng":-84.32649,"kind":"restaurant","cuisine":"ice cream"},{"name":"La Parilla","lat":33.80338,"lng":-84.41254,"kind":"restaurant","cuisine":"mexican"},{"name":"The Dancing Goats Coffee Bar @ Ponce City Market","lat":33.77146,"lng":-84.36739,"kind":"cafe","cuisine":"coffee shop"},{"name":"Mediterranean Grill","lat":33.78126,"lng":-84.36832,"kind":"restaurant","cuisine":"kebab"},{"name":"Q Korean BBQ Revolving Sushi","lat":33.79266,"lng":-84.30506,"kind":"restaurant","cuisine":"indian"},{"name":"Hong Kong Buffett","lat":33.75802,"lng":-84.38963,"kind":"restaurant","cuisine":"chinese"},{"name":"Thrive Restaurant & Bar","lat":33.75697,"lng":-84.39234,"kind":"restaurant","cuisine":"american"},{"name":"Just Around the Corner","lat":33.75719,"lng":-84.39265,"kind":"cafe","cuisine":"burger"},{"name":"Rosa","lat":33.78716,"lng":-84.35571,"kind":"restaurant","cuisine":"mexican"},{"name":"Mali","lat":33.78738,"lng":-84.35571,"kind":"restaurant","cuisine":"thai"},{"name":"San Francisco Coffee","lat":33.78726,"lng":-84.35553,"kind":"cafe","cuisine":"coffee shop"},{"name":"George's","lat":33.78302,"lng":-84.35423,"kind":"restaurant","cuisine":"burger"},{"name":"Murphy's","lat":33.78206,"lng":-84.35488,"kind":"restaurant","cuisine":"american"},{"name":"Ela","lat":33.78687,"lng":-84.35546,"kind":"restaurant","cuisine":"mediterranean"},{"name":"Highland Tap","lat":33.78253,"lng":-84.35453,"kind":"restaurant","cuisine":"steak house"},{"name":"Bar.bacoa","lat":33.78251,"lng":-84.35468,"kind":"restaurant","cuisine":"spanish"},{"name":"Fontaine's","lat":33.7826,"lng":-84.35453,"kind":"restaurant","cuisine":"seafood"},{"name":"Atkin's Park","lat":33.77614,"lng":-84.35268,"kind":"restaurant","cuisine":"american"},{"name":"Surin","lat":33.77658,"lng":-84.35254,"kind":"restaurant","cuisine":"thai"},{"name":"Ocean Wave Sushi By Harry and Sons","lat":33.77692,"lng":-84.35266,"kind":"restaurant","cuisine":"sushi"},{"name":"Osteria 832","lat":33.77723,"lng":-84.35285,"kind":"restaurant","cuisine":"italian"},{"name":"Papi's","lat":33.7728,"lng":-84.38037,"kind":"restaurant","cuisine":"cuban"},{"name":"Marlow's Tavern","lat":33.80118,"lng":-84.32814,"kind":"restaurant","cuisine":"american"},{"name":"Tin Lizzy's","lat":33.80115,"lng":-84.32781,"kind":"restaurant","cuisine":"mexican"},{"name":"Wisteria","lat":33.76679,"lng":-84.35285,"kind":"restaurant","cuisine":"american"},{"name":"Shorty's","lat":33.81783,"lng":-84.31018,"kind":"restaurant","cuisine":"pizza"},{"name":"La Parilla","lat":33.81481,"lng":-84.31087,"kind":"restaurant","cuisine":"mexican"},{"name":"Rathbun's Steak","lat":33.75921,"lng":-84.3639,"kind":"restaurant","cuisine":"steak house"},{"name":"Two Urban Licks","lat":33.7685,"lng":-84.3613,"kind":"restaurant","cuisine":"american"},{"name":"Real Chow Baby","lat":33.77409,"lng":-84.36178,"kind":"restaurant","cuisine":"chinese"},{"name":"Romeo's NY","lat":33.78861,"lng":-84.32656,"kind":"restaurant","cuisine":"pizza"},{"name":"Dave's Cosmic Subs","lat":33.78792,"lng":-84.32761,"kind":"restaurant","cuisine":"sandwich"},{"name":"Falafel King","lat":33.78843,"lng":-84.32636,"kind":"restaurant","cuisine":"kebab"},{"name":"Little Azios","lat":33.73392,"lng":-84.34949,"kind":"restaurant","cuisine":"pizza"},{"name":"Jason's Deli","lat":33.78194,"lng":-84.37997,"kind":"restaurant","cuisine":"sandwich"},{"name":"Flying Biscuit","lat":33.78192,"lng":-84.38028,"kind":"restaurant","cuisine":"american"},{"name":"Caribou Coffee","lat":33.78208,"lng":-84.38064,"kind":"cafe","cuisine":"coffee shop"},{"name":"Souper Jenny Westside","lat":33.78878,"lng":-84.42292,"kind":"restaurant","cuisine":"regional"},{"name":"Thaicoon","lat":33.80445,"lng":-84.33562,"kind":"restaurant","cuisine":"sushi"},{"name":"Starbucks","lat":33.82743,"lng":-84.33134,"kind":"cafe","cuisine":"coffee shop"},{"name":"Cafe Bombay Indian Bistro","lat":33.82844,"lng":-84.32699,"kind":"restaurant","cuisine":"indian"},{"name":"Red Pepper Taqueria","lat":33.81635,"lng":-84.33433,"kind":"restaurant","cuisine":"mexican"},{"name":"Serpas","lat":33.75741,"lng":-84.36737,"kind":"restaurant","cuisine":"american"},{"name":"Sweet Cheats","lat":33.75044,"lng":-84.36439,"kind":"cafe","cuisine":"cupcake"},{"name":"Carrol Street Cafe","lat":33.74897,"lng":-84.36794,"kind":"restaurant","cuisine":"american"},{"name":"Starbucks","lat":33.78695,"lng":-84.38296,"kind":"cafe","cuisine":"coffee shop"},{"name":"Silver Skillet","lat":33.78628,"lng":-84.39428,"kind":"restaurant","cuisine":"american"},{"name":"Rocky Mountain Pizza","lat":33.78212,"lng":-84.40435,"kind":"restaurant","cuisine":"pizza"},{"name":"Gio's Chicken Amalfitano","lat":33.7849,"lng":-84.40583,"kind":"restaurant","cuisine":"italian"},{"name":"Antico Pizza Napoletana","lat":33.78466,"lng":-84.40563,"kind":"restaurant","cuisine":"pizza"},{"name":"Shake Shack","lat":33.78541,"lng":-84.41214,"kind":"restaurant","cuisine":"burger"},{"name":"Die Biergarten","lat":33.7619,"lng":-84.39664,"kind":"restaurant","cuisine":"german"},{"name":"Stats","lat":33.76128,"lng":-84.39626,"kind":"restaurant","cuisine":"american"},{"name":"Fresh2Order","lat":33.80094,"lng":-84.32814,"kind":"restaurant","cuisine":"american"},{"name":"General Muir","lat":33.80116,"lng":-84.32713,"kind":"restaurant","cuisine":"deli"},{"name":"Honey Bubble","lat":33.77413,"lng":-84.36134,"kind":"cafe","cuisine":"bubble tea"},{"name":"Tin Drum","lat":33.7767,"lng":-84.39005,"kind":"restaurant","cuisine":"asian"},{"name":"White Oak","lat":33.76213,"lng":-84.38786,"kind":"restaurant","cuisine":"american"},{"name":"Talkin' Tacos","lat":33.82641,"lng":-84.36549,"kind":"restaurant","cuisine":"burger"},{"name":"Pacific Rim Bistro","lat":33.76243,"lng":-84.38585,"kind":"restaurant","cuisine":"asian"},{"name":"Big Kahuna Grill","lat":33.7628,"lng":-84.38585,"kind":"restaurant","cuisine":"mexican"},{"name":"The Sun Dial Restaurant & View","lat":33.75943,"lng":-84.38858,"kind":"restaurant","cuisine":"american"},{"name":"Anatolia Mediterranean Cafe","lat":33.75518,"lng":-84.38928,"kind":"restaurant","cuisine":"mediterranean"},{"name":"Rising Roll Gourmet Cafe","lat":33.75666,"lng":-84.38808,"kind":"restaurant","cuisine":"sandwich"},{"name":"Bistro Niko","lat":33.84656,"lng":-84.36857,"kind":"restaurant","cuisine":"french"},{"name":"Café Lucia","lat":33.78414,"lng":-84.38057,"kind":"cafe","cuisine":"pastry"},{"name":"Anh’s Kitchen","lat":33.77797,"lng":-84.38412,"kind":"restaurant","cuisine":"vietnamese"},{"name":"Circle Poké","lat":33.78205,"lng":-84.40782,"kind":"restaurant","cuisine":"asian"},{"name":"Lucky Buddha","lat":33.78186,"lng":-84.40478,"kind":"restaurant","cuisine":"chinese"},{"name":"Pizza Hut","lat":33.78185,"lng":-84.4052,"kind":"restaurant","cuisine":"pizza"},{"name":"CAVA","lat":33.7775,"lng":-84.38422,"kind":"restaurant","cuisine":"mediterranean"},{"name":"Rush Bowls","lat":33.77782,"lng":-84.38414,"kind":"restaurant","cuisine":"yogurt"},{"name":"Kale Me Crazy","lat":33.76288,"lng":-84.35842,"kind":"restaurant","cuisine":"juice"},{"name":"Pure Taqueria","lat":33.76301,"lng":-84.35828,"kind":"restaurant","cuisine":"mexican"},{"name":"The Daily","lat":33.75699,"lng":-84.35399,"kind":"cafe","cuisine":"breakfast"},{"name":"Smokey Stallion BBQ Bistro","lat":33.75218,"lng":-84.39809,"kind":"restaurant","cuisine":"barbecue"},{"name":"Slice","lat":33.75691,"lng":-84.39012,"kind":"restaurant","cuisine":"pizza"},{"name":"Barnes & Noble Cafe","lat":33.8801,"lng":-84.46378,"kind":"cafe","cuisine":"coffee shop"},{"name":"The Original ChopShop","lat":33.87989,"lng":-84.461,"kind":"cafe","cuisine":"american"},{"name":"Fresh To Order","lat":33.77826,"lng":-84.38456,"kind":"restaurant","cuisine":"american"},{"name":"Mellow Mushroom","lat":33.86132,"lng":-84.34006,"kind":"restaurant","cuisine":"pizza"},{"name":"Mezza Luna Pasta & Seafood","lat":33.88281,"lng":-84.50485,"kind":"restaurant","cuisine":"italian"},{"name":"US Cafe Express","lat":33.88244,"lng":-84.48723,"kind":"restaurant","cuisine":"burger"},{"name":"LongHorn Steakhouse","lat":33.88104,"lng":-84.46031,"kind":"restaurant","cuisine":"steak house"},{"name":"Philly Connection","lat":33.87991,"lng":-84.46123,"kind":"restaurant","cuisine":"sandwich"},{"name":"Mint Leaf Indian Cuisine","lat":33.88251,"lng":-84.4867,"kind":"restaurant","cuisine":"indian"},{"name":"Jamaica-MikrazY","lat":33.88356,"lng":-84.48032,"kind":"restaurant","cuisine":"jamaican"},{"name":"Taco Cantina","lat":33.88355,"lng":-84.48066,"kind":"restaurant","cuisine":"mexican"},{"name":"Minato Japanese Restaurant","lat":33.88443,"lng":-84.47535,"kind":"restaurant","cuisine":"japanese"},{"name":"Hawaiian BBQ","lat":33.81661,"lng":-84.33569,"kind":"restaurant","cuisine":"hawaiian"},{"name":"Maddio's","lat":33.81429,"lng":-84.30984,"kind":"restaurant","cuisine":"pizza"},{"name":"Chris's","lat":33.81593,"lng":-84.31241,"kind":"restaurant","cuisine":"mediterranean"},{"name":"Mediteranean Grill","lat":33.79061,"lng":-84.30502,"kind":"restaurant","cuisine":"mediterranean"},{"name":"The Dancing Goats Coffee Bar","lat":33.77581,"lng":-84.30327,"kind":"cafe","cuisine":"coffee shop"},{"name":"The Optimist","lat":33.77985,"lng":-84.41065,"kind":"restaurant","cuisine":"seafood"},{"name":"Starbucks","lat":33.83538,"lng":-84.38269,"kind":"cafe","cuisine":"coffee shop"},{"name":"Avellino's","lat":33.88102,"lng":-84.34266,"kind":"restaurant","cuisine":"italian"},{"name":"Bhojanic","lat":33.84603,"lng":-84.36557,"kind":"restaurant","cuisine":"indian"},{"name":"Dantanna's","lat":33.8476,"lng":-84.36517,"kind":"restaurant","cuisine":"steak house"},{"name":"The Cheesecake Factory","lat":33.84824,"lng":-84.36279,"kind":"restaurant","cuisine":"american"},{"name":"Folk Art","lat":33.76664,"lng":-84.35297,"kind":"restaurant","cuisine":"american"},{"name":"Le Petit Marche","lat":33.75148,"lng":-84.32256,"kind":"restaurant","cuisine":"breakfast"},{"name":"Dos Madres Cantina","lat":33.77545,"lng":-84.30116,"kind":"restaurant","cuisine":"mexican"},{"name":"Arden's Garden","lat":33.75095,"lng":-84.32186,"kind":"restaurant","cuisine":"juice"},{"name":"Taproom Coffee","lat":33.75157,"lng":-84.32321,"kind":"cafe","cuisine":"coffee shop"},{"name":"C&S Seafood & Oyster Bar","lat":33.87257,"lng":-84.45761,"kind":"restaurant","cuisine":"seafood"},{"name":"Pho 24","lat":33.87758,"lng":-84.29335,"kind":"restaurant","cuisine":"vietnamese"},{"name":"Blaze Pizza","lat":33.8828,"lng":-84.46197,"kind":"restaurant","cuisine":"pizza"},{"name":"Doc Green's","lat":33.88242,"lng":-84.46215,"kind":"restaurant","cuisine":"salad"},{"name":"Top Spice","lat":33.88101,"lng":-84.45841,"kind":"restaurant","cuisine":"thai"},{"name":"Zucca Bar & Pizzeria","lat":33.88375,"lng":-84.51473,"kind":"restaurant","cuisine":"pizza"},{"name":"Varuni Napoli Pizza","lat":33.79656,"lng":-84.36876,"kind":"restaurant","cuisine":"pizza"},{"name":"Sweet Monkey","lat":33.80118,"lng":-84.32745,"kind":"restaurant","cuisine":"yogurt"},{"name":"Urban Grind","lat":33.7777,"lng":-84.40898,"kind":"cafe","cuisine":"coffee shop"},{"name":"Hoki Japanese Restaurant","lat":33.87243,"lng":-84.45787,"kind":"restaurant","cuisine":"japanese"},{"name":"Willy's Mexicana Grill","lat":33.75119,"lng":-84.38542,"kind":"restaurant","cuisine":"mexican"},{"name":"Brasserie Lundi","lat":33.79252,"lng":-84.38605,"kind":"restaurant","cuisine":"french"},{"name":"The Pig & The Pearl","lat":33.79338,"lng":-84.3977,"kind":"restaurant","cuisine":"american"},{"name":"Chololaté","lat":33.79126,"lng":-84.30582,"kind":"cafe","cuisine":"coffee shop"},{"name":"Melinated Cafe","lat":33.75021,"lng":-84.39529,"kind":"restaurant","cuisine":"american"},{"name":"So Ba Vietnamese Restaurant","lat":33.73945,"lng":-84.34566,"kind":"restaurant","cuisine":"vietnamese"},{"name":"Blu Cantina","lat":33.74034,"lng":-84.34688,"kind":"restaurant","cuisine":"mexican"},{"name":"Sushi Matsuya","lat":33.81586,"lng":-84.31289,"kind":"restaurant","cuisine":"japanese"},{"name":"Atlanta Coffee Roasters","lat":33.81584,"lng":-84.31305,"kind":"cafe","cuisine":"coffee shop"},{"name":"Napoleon's Grill","lat":33.82574,"lng":-84.2906,"kind":"restaurant","cuisine":"american"},{"name":"Crazy Cuban","lat":33.78602,"lng":-84.39653,"kind":"restaurant","cuisine":"cuban"},{"name":"Fred's Meat & Bread","lat":33.75687,"lng":-84.36397,"kind":"restaurant","cuisine":"sandwich"},{"name":"Casseroles To Go","lat":33.79216,"lng":-84.35218,"kind":"restaurant","cuisine":"american"},{"name":"Twisted Soul Cookhouse & Pours","lat":33.78921,"lng":-84.42526,"kind":"restaurant","cuisine":"southern"},{"name":"Bartaco","lat":33.86518,"lng":-84.46754,"kind":"restaurant","cuisine":"mexican"},{"name":"Mellow Mushroom","lat":33.86508,"lng":-84.46771,"kind":"restaurant","cuisine":"pizza"},{"name":"Bon Ton","lat":33.77296,"lng":-84.38038,"kind":"restaurant","cuisine":"seafood"},{"name":"Pera Bistro","lat":33.81168,"lng":-84.42444,"kind":"restaurant","cuisine":"mediterranean"},{"name":"1201 Restaurant","lat":33.81163,"lng":-84.42504,"kind":"restaurant","cuisine":"american"},{"name":"Whitehall Tavern","lat":33.82018,"lng":-84.38766,"kind":"restaurant","cuisine":"american"},{"name":"Pasta Vino","lat":33.82017,"lng":-84.38744,"kind":"restaurant","cuisine":"italian"},{"name":"SIP The Experience","lat":33.82273,"lng":-84.36987,"kind":"cafe","cuisine":"coffee shop"},{"name":"Valenza","lat":33.86073,"lng":-84.32999,"kind":"restaurant","cuisine":"italian"},{"name":"Gus's Fried Chicken","lat":33.75992,"lng":-84.38622,"kind":"restaurant","cuisine":"chicken"},{"name":"BoccaLupa","lat":33.75478,"lng":-84.36276,"kind":"restaurant","cuisine":"italian"},{"name":"Lady Bird","lat":33.75961,"lng":-84.36422,"kind":"restaurant","cuisine":"american"},{"name":"Sushi Avenue","lat":33.77446,"lng":-84.29581,"kind":"restaurant","cuisine":"japanese"},{"name":"CM Chicken & Ssong's Hotdogs","lat":33.78185,"lng":-84.40468,"kind":"restaurant","cuisine":"korean"},{"name":"Cafe Antico","lat":33.78421,"lng":-84.40541,"kind":"restaurant","cuisine":"italian"},{"name":"Sophie's Uptown","lat":33.83694,"lng":-84.38347,"kind":"restaurant","cuisine":"deli"},{"name":"The Cookie Studio","lat":33.83696,"lng":-84.38294,"kind":"restaurant","cuisine":"bakery"},{"name":"Brio","lat":33.8357,"lng":-84.38245,"kind":"restaurant","cuisine":"italian"},{"name":"Raja Indian","lat":33.83549,"lng":-84.38172,"kind":"restaurant","cuisine":"indian"},{"name":"Canton Buddha","lat":33.83435,"lng":-84.3837,"kind":"restaurant","cuisine":"chinese"},{"name":"Barberitos","lat":33.83373,"lng":-84.38431,"kind":"restaurant","cuisine":"mexican"},{"name":"Your Pie","lat":33.83975,"lng":-84.38042,"kind":"restaurant","cuisine":"pizza"},{"name":"King + Duke","lat":33.83922,"lng":-84.38072,"kind":"restaurant","cuisine":"american"},{"name":"American Cut","lat":33.83736,"lng":-84.38104,"kind":"restaurant","cuisine":"steak house"},{"name":"Le Bilboquet","lat":33.83768,"lng":-84.38034,"kind":"restaurant","cuisine":"french"},{"name":"Starbucks","lat":33.87757,"lng":-84.46553,"kind":"cafe","cuisine":"coffee shop"},{"name":"Starbucks","lat":33.77664,"lng":-84.38835,"kind":"cafe","cuisine":"coffee shop"},{"name":"Maggiano's Little Italy","lat":33.84817,"lng":-84.36736,"kind":"restaurant","cuisine":"american"},{"name":"drip","lat":33.65887,"lng":-84.40868,"kind":"cafe","cuisine":"coffee shop"},{"name":"Sprig","lat":33.82569,"lng":-84.28946,"kind":"restaurant","cuisine":"american"},{"name":"La Fonda Latina","lat":33.75123,"lng":-84.30991,"kind":"restaurant","cuisine":"mexican"},{"name":"Superica","lat":33.7571,"lng":-84.36418,"kind":"restaurant","cuisine":"mexican"},{"name":"Zumi","lat":33.76119,"lng":-84.36523,"kind":"restaurant","cuisine":"sushi"},{"name":"Olive Bistro","lat":33.77396,"lng":-84.36587,"kind":"restaurant","cuisine":"mediterranean"},{"name":"Metro Fresh","lat":33.78023,"lng":-84.36836,"kind":"restaurant","cuisine":"sandwich"},{"name":"Chin Chin II On Ponce","lat":33.77314,"lng":-84.36399,"kind":"restaurant","cuisine":"chinese"},{"name":"Jia","lat":33.7729,"lng":-84.36594,"kind":"restaurant","cuisine":"chinese"},{"name":"Rising Roll Gourmet Café","lat":33.78708,"lng":-84.3882,"kind":"cafe","cuisine":"sandwich"},{"name":"Corner Bakery","lat":33.76182,"lng":-84.38784,"kind":"cafe","cuisine":"coffee shop"},{"name":"JINYA Ramen Bar","lat":33.85666,"lng":-84.38278,"kind":"restaurant","cuisine":"ramen"},{"name":"Urban HAI Chinese","lat":33.78409,"lng":-84.38463,"kind":"restaurant","cuisine":"chinese"},{"name":"Grant Central Pizza","lat":33.74222,"lng":-84.37352,"kind":"restaurant","cuisine":"pizza"},{"name":"Boruboru Sushi","lat":33.80079,"lng":-84.32662,"kind":"restaurant","cuisine":"japanese"},{"name":"Aladdin's","lat":33.80069,"lng":-84.32644,"kind":"restaurant","cuisine":"mediterranean"},{"name":"Papi's Cuban Grill","lat":33.80105,"lng":-84.32715,"kind":"restaurant","cuisine":"cuban"},{"name":"Paradise Biryani","lat":33.80092,"lng":-84.32728,"kind":"restaurant","cuisine":"indian"},{"name":"Chow Mei Mei","lat":33.80092,"lng":-84.32758,"kind":"restaurant","cuisine":"chinese"},{"name":"Agavero Cantina","lat":33.78921,"lng":-84.4256,"kind":"restaurant","cuisine":"mexican"},{"name":"Cafe Lucia","lat":33.75572,"lng":-84.38988,"kind":"cafe","cuisine":"coffee shop"},{"name":"Condesa Coffee","lat":33.75974,"lng":-84.37186,"kind":"cafe","cuisine":"coffee shop"},{"name":"LottaFrutta","lat":33.75592,"lng":-84.36809,"kind":"restaurant","cuisine":"sandwich"},{"name":"Tio Lucho's","lat":33.77304,"lng":-84.35239,"kind":"restaurant","cuisine":"peruvian"},{"name":"Simon's Restaurant","lat":33.77613,"lng":-84.38262,"kind":"restaurant","cuisine":"burger"},{"name":"Babs Midtown","lat":33.77675,"lng":-84.38316,"kind":"restaurant","cuisine":"burger"},{"name":"Food Terminal","lat":33.77876,"lng":-84.41016,"kind":"restaurant","cuisine":"asian"},{"name":"Land of 1000 Hills","lat":33.7558,"lng":-84.38892,"kind":"cafe","cuisine":"coffee shop"},{"name":"Highland Bakery","lat":33.75542,"lng":-84.38781,"kind":"restaurant","cuisine":"bakery"},{"name":"Yumbi","lat":33.80736,"lng":-84.39351,"kind":"restaurant","cuisine":"asian"},{"name":"57th Fighter Group","lat":33.87257,"lng":-84.30563,"kind":"restaurant","cuisine":"american"},{"name":"Satto Thai and Sushi Bar","lat":33.77318,"lng":-84.40384,"kind":"restaurant","cuisine":"asian"},{"name":"Starbucks","lat":33.78918,"lng":-84.32677,"kind":"cafe","cuisine":"coffee shop"},{"name":"La Costilla Grill","lat":33.85871,"lng":-84.30911,"kind":"restaurant","cuisine":"mexican"},{"name":"Mariscos El Malecon","lat":33.85838,"lng":-84.30929,"kind":"restaurant","cuisine":"seafood"},{"name":"Yo! Chef What's cooking?","lat":33.85879,"lng":-84.3091,"kind":"restaurant","cuisine":"cuban"},{"name":"Naan Stop","lat":33.84801,"lng":-84.374,"kind":"restaurant","cuisine":"indian"},{"name":"Twin Peaks","lat":33.84741,"lng":-84.37288,"kind":"restaurant","cuisine":"american"},{"name":"Porfirio's Mexican Bar & Grill","lat":33.76238,"lng":-84.38793,"kind":"restaurant","cuisine":"mexican"},{"name":"Da Vinci's Pizzeria","lat":33.8833,"lng":-84.50085,"kind":"restaurant","cuisine":"pizza"},{"name":"Wagaya","lat":33.78636,"lng":-84.39836,"kind":"restaurant","cuisine":"japanese"},{"name":"Sweet Hut Bakery","lat":33.78007,"lng":-84.38398,"kind":"cafe","cuisine":"cake"},{"name":"Le Fat","lat":33.7782,"lng":-84.40894,"kind":"restaurant","cuisine":"vietnamese"},{"name":"Dancing Goats Coffee","lat":33.78057,"lng":-84.38642,"kind":"cafe","cuisine":"coffee shop"},{"name":"Rreal Tacos","lat":33.78178,"lng":-84.40786,"kind":"restaurant","cuisine":"mexican"},{"name":"Bartaco","lat":33.7789,"lng":-84.40946,"kind":"restaurant","cuisine":"tacos"},{"name":"One Georgia Center Cafeteria","lat":33.77068,"lng":-84.38775,"kind":"cafe","cuisine":"chicken"},{"name":"Gold & Bold Coffee Roasters","lat":33.78072,"lng":-84.39798,"kind":"cafe","cuisine":"coffee shop"},{"name":"Blue Donkey Coffee","lat":33.7743,"lng":-84.3953,"kind":"cafe","cuisine":"coffee shop"},{"name":"Superica","lat":33.85992,"lng":-84.38108,"kind":"restaurant","cuisine":"mexican"},{"name":"Hal’s Steakhouse","lat":33.85469,"lng":-84.38169,"kind":"restaurant","cuisine":"steak house"},{"name":"Bar Taco","lat":33.85837,"lng":-84.38148,"kind":"restaurant","cuisine":"mexican"},{"name":"Starbucks","lat":33.88394,"lng":-84.31612,"kind":"cafe","cuisine":"coffee shop"},{"name":"Buffalo Wild Wings","lat":33.8426,"lng":-84.32841,"kind":"restaurant","cuisine":"wings"},{"name":"1st Wok","lat":33.84385,"lng":-84.32834,"kind":"restaurant","cuisine":"chinese"},{"name":"rise-n-dine","lat":33.78793,"lng":-84.32635,"kind":"restaurant","cuisine":"american"},{"name":"Lucky’s Burger & Brew","lat":33.78796,"lng":-84.32625,"kind":"restaurant","cuisine":"american"},{"name":"Double Zero","lat":33.78798,"lng":-84.32617,"kind":"restaurant","cuisine":"italian"},{"name":"Wagaya","lat":33.78802,"lng":-84.32604,"kind":"restaurant","cuisine":"japanese"},{"name":"Golden Drops Cafe","lat":33.80621,"lng":-84.3108,"kind":"cafe","cuisine":"coffee shop"},{"name":"Kung Fu Tea","lat":33.75439,"lng":-84.38845,"kind":"cafe","cuisine":"bubble tea"},{"name":"Kale Me Crazy","lat":33.77741,"lng":-84.38303,"kind":"restaurant","cuisine":"sandwich"},{"name":"Bachi Box","lat":33.77804,"lng":-84.38462,"kind":"restaurant","cuisine":"asian"},{"name":"Ecco Midtown","lat":33.77878,"lng":-84.38588,"kind":"restaurant","cuisine":"european"},{"name":"China Moon","lat":33.86501,"lng":-84.46976,"kind":"restaurant","cuisine":"chinese"},{"name":"Cafe at Pharr","lat":33.865,"lng":-84.46671,"kind":"restaurant","cuisine":"sandwich"},{"name":"La Mixteca Tamale House","lat":33.80693,"lng":-84.43422,"kind":"restaurant","cuisine":"mexican"},{"name":"Red Pepper Taqueria","lat":33.86967,"lng":-84.33598,"kind":"restaurant","cuisine":"mexican"},{"name":"La Pastorcita","lat":33.84298,"lng":-84.32924,"kind":"restaurant","cuisine":"mexican"},{"name":"Desta Ethiopian Kitchen","lat":33.8379,"lng":-84.31031,"kind":"restaurant","cuisine":"ethiopian"},{"name":"Jason's Deli","lat":33.84645,"lng":-84.37446,"kind":"restaurant","cuisine":"sandwich"},{"name":"Truva Turkish Kitchen","lat":33.77747,"lng":-84.35274,"kind":"restaurant","cuisine":"regional"},{"name":"Tin Drum Asian Kitchen","lat":33.88271,"lng":-84.46201,"kind":"restaurant","cuisine":"asian"},{"name":"Pizza Hut","lat":33.72168,"lng":-84.34804,"kind":"restaurant","cuisine":"pizza"},{"name":"Starbucks","lat":33.77499,"lng":-84.389,"kind":"cafe","cuisine":"coffee shop"},{"name":"Starbucks","lat":33.76039,"lng":-84.3948,"kind":"cafe","cuisine":"coffee shop"},{"name":"Amalfi Pizza","lat":33.75959,"lng":-84.38698,"kind":"restaurant","cuisine":"pizza"},{"name":"Cuts Steakhouse","lat":33.75985,"lng":-84.38577,"kind":"restaurant","cuisine":"steak house"},{"name":"Pho King Midtown","lat":33.78017,"lng":-84.38753,"kind":"restaurant","cuisine":"vietnamese"},{"name":"Sceptre Brewing Arts","lat":33.76033,"lng":-84.30479,"kind":"restaurant","cuisine":"american"},{"name":"East Pole Coffee Company","lat":33.8107,"lng":-84.3785,"kind":"cafe","cuisine":"coffee"},{"name":"Starbucks","lat":33.75437,"lng":-84.38672,"kind":"cafe","cuisine":"coffee shop"},{"name":"Pizza Hut","lat":33.8799,"lng":-84.46199,"kind":"restaurant","cuisine":"pizza"},{"name":"Mellow Mushroom","lat":33.76493,"lng":-84.38874,"kind":"restaurant","cuisine":"pizza"},{"name":"Tin Lizzy's Cantina","lat":33.74657,"lng":-84.37388,"kind":"restaurant","cuisine":"mexican"},{"name":"Six Feet Under Pub & Fish House","lat":33.74663,"lng":-84.37277,"kind":"restaurant","cuisine":"seafood"},{"name":"Waffle House","lat":33.74738,"lng":-84.29118,"kind":"restaurant","cuisine":"american"},{"name":"Nam Phuong","lat":33.86124,"lng":-84.3079,"kind":"restaurant","cuisine":"vietnamese"},{"name":"Fadó Irish Pub","lat":33.77963,"lng":-84.38404,"kind":"restaurant","cuisine":"american"},{"name":"Trade Root Restaurant & Lounge","lat":33.85029,"lng":-84.36306,"kind":"restaurant","cuisine":"mediterranean"},{"name":"Park Grounds","lat":33.7501,"lng":-84.35465,"kind":"cafe","cuisine":"coffee shop"},{"name":"New York Prime","lat":33.85159,"lng":-84.3643,"kind":"restaurant","cuisine":"steak house"},{"name":"Talat Market","lat":33.73176,"lng":-84.38397,"kind":"restaurant","cuisine":"thai"},{"name":"Mr. Hibachi","lat":33.75436,"lng":-84.38832,"kind":"restaurant","cuisine":"asian"},{"name":"Buenas Dias Cafe","lat":33.75385,"lng":-84.38868,"kind":"restaurant","cuisine":"mexican"},{"name":"Alma Cocina","lat":33.75919,"lng":-84.3874,"kind":"restaurant","cuisine":"mexican"},{"name":"Pokeworks","lat":33.87991,"lng":-84.46165,"kind":"restaurant","cuisine":"poke"},{"name":"Cypress Street Pint and Plate","lat":33.77735,"lng":-84.38611,"kind":"restaurant","cuisine":"american"},{"name":"Trader Vic's Atlanta","lat":33.76106,"lng":-84.3833,"kind":"restaurant","cuisine":"polynesian"},{"name":"Hudson Grille","lat":33.75733,"lng":-84.39332,"kind":"restaurant","cuisine":"american"},{"name":"Bite of Korea","lat":33.76381,"lng":-84.36808,"kind":"restaurant","cuisine":"korean"},{"name":"LongHorn Steakhouse","lat":33.81717,"lng":-84.31097,"kind":"restaurant","cuisine":"steak house"},{"name":"Outback Steakhouse","lat":33.81676,"lng":-84.3153,"kind":"restaurant","cuisine":"american"},{"name":"Chili's","lat":33.81635,"lng":-84.31574,"kind":"restaurant","cuisine":"tex-mex"},{"name":"Taziki's Mediterranean Cafe","lat":33.81422,"lng":-84.30984,"kind":"restaurant","cuisine":"greek"},{"name":"Vinny's N.Y. Pizza","lat":33.77831,"lng":-84.38483,"kind":"restaurant","cuisine":"pizza"},{"name":"Starbucks","lat":33.7927,"lng":-84.3994,"kind":"cafe","cuisine":"coffee shop"},{"name":"TUK TUK Thai Food Loft","lat":33.80161,"lng":-84.3925,"kind":"restaurant","cuisine":"thai"},{"name":"Grana","lat":33.80592,"lng":-84.36689,"kind":"restaurant","cuisine":"italian"},{"name":"Little Rey “Al Carbon”","lat":33.80798,"lng":-84.36631,"kind":"restaurant","cuisine":"mexican"},{"name":"Taste of Tropical","lat":33.74098,"lng":-84.41721,"kind":"restaurant","cuisine":"caribbean"},{"name":"Buffalo Wild Wings","lat":33.65628,"lng":-84.51145,"kind":"restaurant","cuisine":"wings"},{"name":"Starbucks","lat":33.84938,"lng":-84.42825,"kind":"cafe","cuisine":"coffee shop"},{"name":"Pizza Hut","lat":33.68798,"lng":-84.40893,"kind":"restaurant","cuisine":"pizza"},{"name":"Moonsoon Masala","lat":33.85904,"lng":-84.30907,"kind":"restaurant","cuisine":"chinese"},{"name":"Little Lagos","lat":33.8586,"lng":-84.30913,"kind":"restaurant","cuisine":"african"},{"name":"Hong Kong City","lat":33.85855,"lng":-84.30914,"kind":"restaurant","cuisine":"chinese"},{"name":"Café Lucia","lat":33.88411,"lng":-84.51567,"kind":"cafe","cuisine":"coffee shop"},{"name":"The Ashford","lat":33.86097,"lng":-84.33113,"kind":"restaurant","cuisine":"regional"},{"name":"EATaliano Kitchen","lat":33.82828,"lng":-84.33301,"kind":"restaurant","cuisine":"italian"},{"name":"Earl of Sandwich","lat":33.85299,"lng":-84.36289,"kind":"restaurant","cuisine":"sandwich"},{"name":"Eclipse di Luna","lat":33.83199,"lng":-84.36176,"kind":"restaurant","cuisine":"tapas"},{"name":"Sushi Kiku","lat":33.83088,"lng":-84.35682,"kind":"restaurant","cuisine":"sushi"},{"name":"Velvet Taco","lat":33.84,"lng":-84.38102,"kind":"restaurant","cuisine":"mexican"},{"name":"Gene's","lat":33.75095,"lng":-84.30961,"kind":"restaurant","cuisine":"barbecue"},{"name":"Babygirl","lat":33.75067,"lng":-84.30959,"kind":"restaurant","cuisine":"coffee shop"},{"name":"FruTea Bubbles Café","lat":33.88533,"lng":-84.51559,"kind":"cafe","cuisine":"bubble tea"},{"name":"Kaldi's Coffee","lat":33.77423,"lng":-84.39652,"kind":"cafe","cuisine":"coffee shop"},{"name":"Ponko Chicken","lat":33.7735,"lng":-84.29532,"kind":"restaurant","cuisine":"chicken"},{"name":"Cameli's","lat":33.76443,"lng":-84.34894,"kind":"restaurant","cuisine":"pizza"},{"name":"Starbucks","lat":33.75217,"lng":-84.38235,"kind":"cafe","cuisine":"coffee shop"},{"name":"Blue India","lat":33.77963,"lng":-84.38386,"kind":"restaurant","cuisine":"indian"},{"name":"El Tesoro","lat":33.74947,"lng":-84.34259,"kind":"restaurant","cuisine":"mexican"},{"name":"Cuddlefish","lat":33.77352,"lng":-84.29511,"kind":"restaurant","cuisine":"sushi"},{"name":"VN Sandwich","lat":33.87499,"lng":-84.52982,"kind":"restaurant","cuisine":"vietnamese"},{"name":"Mariscos Las Islitas","lat":33.87483,"lng":-84.53011,"kind":"restaurant","cuisine":"mexican"},{"name":"No. 1 China","lat":33.8764,"lng":-84.53287,"kind":"restaurant","cuisine":"chinese"},{"name":"Pita","lat":33.87628,"lng":-84.53336,"kind":"restaurant","cuisine":"greek"},{"name":"Metro Diner & Bar","lat":33.75981,"lng":-84.38639,"kind":"restaurant","cuisine":"american"},{"name":"Wing Factory","lat":33.87048,"lng":-84.37962,"kind":"restaurant","cuisine":"chicken"},{"name":"Taichi Bubble Tea","lat":33.82803,"lng":-84.33213,"kind":"restaurant","cuisine":"noodle"},{"name":"Adios Cafe","lat":33.74989,"lng":-84.40102,"kind":"restaurant","cuisine":"breakfast"},{"name":"¡La Bodega!","lat":33.73636,"lng":-84.41196,"kind":"restaurant","cuisine":"coffee shop"},{"name":"Tin Drum Asian Kitchen","lat":33.82845,"lng":-84.32902,"kind":"restaurant","cuisine":"asian"},{"name":"Michi Ru Asian Cuisine","lat":33.84264,"lng":-84.49832,"kind":"restaurant","cuisine":"asian"},{"name":"Augie's Cafe","lat":33.74322,"lng":-84.43792,"kind":"restaurant","cuisine":"american"},{"name":"El Tesoro","lat":33.73151,"lng":-84.42186,"kind":"restaurant","cuisine":"mexican"},{"name":"Nobu","lat":33.85424,"lng":-84.36323,"kind":"restaurant","cuisine":"sushi"},{"name":"Basil's Restaurant & Tapas Bar","lat":33.83616,"lng":-84.37597,"kind":"restaurant","cuisine":"restaurant"},{"name":"Starbucks","lat":33.65434,"lng":-84.50315,"kind":"cafe","cuisine":"coffee shop"},{"name":"Fortune Cookie Restaurant","lat":33.82657,"lng":-84.33335,"kind":"restaurant","cuisine":"chinese"},{"name":"Glenn's Kitchen","lat":33.75697,"lng":-84.39291,"kind":"restaurant","cuisine":"american"},{"name":"Hoots Wings By Hooters","lat":33.74646,"lng":-84.35766,"kind":"restaurant","cuisine":"wings"},{"name":"Aleppo Kitchen","lat":33.73852,"lng":-84.34448,"kind":"restaurant","cuisine":"syrian"},{"name":"Delbar","lat":33.76143,"lng":-84.3604,"kind":"restaurant","cuisine":"middle eastern"},{"name":"Rancho El Molcajete Mexican Restaurant","lat":33.81675,"lng":-84.56869,"kind":"restaurant","cuisine":"mexican"},{"name":"Curry Up Now","lat":33.74624,"lng":-84.35789,"kind":"restaurant","cuisine":"indian"},{"name":"Muss & Turner's","lat":33.84935,"lng":-84.49184,"kind":"restaurant","cuisine":"american"},{"name":"Old Brick Pit","lat":33.88057,"lng":-84.32032,"kind":"restaurant","cuisine":"barbecue"},{"name":"Whoopsie's","lat":33.75346,"lng":-84.34937,"kind":"restaurant","cuisine":"american"},{"name":"Purely Plant","lat":33.75348,"lng":-84.34958,"kind":"restaurant","cuisine":"taco"},{"name":"Snooze - An A M. Eatery","lat":33.78002,"lng":-84.36784,"kind":"restaurant","cuisine":"american"},{"name":"Wylie & Rum Island Grill","lat":33.75218,"lng":-84.34957,"kind":"restaurant","cuisine":"cuban"},{"name":"La Semilla","lat":33.74682,"lng":-84.36149,"kind":"restaurant","cuisine":"cuban"},{"name":"First Watch","lat":33.74505,"lng":-84.35779,"kind":"restaurant","cuisine":"american"},{"name":"Bacchanalia","lat":33.79471,"lng":-84.42726,"kind":"restaurant","cuisine":"american"},{"name":"Atlas","lat":33.83996,"lng":-84.38269,"kind":"restaurant","cuisine":"american"},{"name":"Hayakawa","lat":33.78334,"lng":-84.41142,"kind":"restaurant","cuisine":"japanese"},{"name":"Mujō","lat":33.78611,"lng":-84.41066,"kind":"restaurant","cuisine":"japanese"},{"name":"Bomb Biscuit Co.","lat":33.76144,"lng":-84.36535,"kind":"restaurant","cuisine":"breakfast"},{"name":"Fishmonger","lat":33.7728,"lng":-84.35269,"kind":"restaurant","cuisine":"seafood"},{"name":"Snooze","lat":33.87971,"lng":-84.38091,"kind":"restaurant","cuisine":"breakfast"},{"name":"D92","lat":33.77196,"lng":-84.29379,"kind":"restaurant","cuisine":"korean"},{"name":"HandleBar","lat":33.75443,"lng":-84.37203,"kind":"restaurant","cuisine":"american"},{"name":"Fox Bros BBQ","lat":33.86133,"lng":-84.33978,"kind":"restaurant","cuisine":"barbecue"},{"name":"Kaleidoscope","lat":33.8609,"lng":-84.33182,"kind":"restaurant","cuisine":"american"},{"name":"Verde","lat":33.861,"lng":-84.33094,"kind":"restaurant","cuisine":"mexican"},{"name":"Haven","lat":33.86064,"lng":-84.33052,"kind":"restaurant","cuisine":"american"},{"name":"Vero Pizzeria","lat":33.86074,"lng":-84.33016,"kind":"restaurant","cuisine":"pizza"},{"name":"J. Christopher's","lat":33.86112,"lng":-84.33003,"kind":"restaurant","cuisine":"breakfast"},{"name":"Galla's Pizza","lat":33.88167,"lng":-84.31882,"kind":"restaurant","cuisine":"pizza"},{"name":"RUCHI BAngladeshi Cuisine","lat":33.88148,"lng":-84.31914,"kind":"restaurant","cuisine":"asian"},{"name":"Starbucks","lat":33.88432,"lng":-84.31599,"kind":"cafe","cuisine":"coffee shop"},{"name":"CAVA","lat":33.88481,"lng":-84.31564,"kind":"restaurant","cuisine":"mediterranean"},{"name":"Bangkok Street Food","lat":33.88381,"lng":-84.316,"kind":"restaurant","cuisine":"thai"},{"name":"Taqueria del Sol","lat":33.88367,"lng":-84.31594,"kind":"restaurant","cuisine":"mexican"},{"name":"gusto!","lat":33.88375,"lng":-84.31642,"kind":"restaurant","cuisine":"american"},{"name":"Tim Hortons","lat":33.77067,"lng":-84.38929,"kind":"cafe","cuisine":"coffee shop"},{"name":"Okiboru Tsukemen & Ramen","lat":33.81614,"lng":-84.39027,"kind":"restaurant","cuisine":"japanese"},{"name":"Rreal Tacos","lat":33.77742,"lng":-84.38347,"kind":"restaurant","cuisine":"mexican"},{"name":"Lantana","lat":33.78697,"lng":-84.3813,"kind":"restaurant","cuisine":"american"},{"name":"Sister","lat":33.84793,"lng":-84.36633,"kind":"restaurant","cuisine":"sandwich"},{"name":"Nick's Food To Go","lat":33.74753,"lng":-84.3797,"kind":"restaurant","cuisine":"greek"},{"name":"Mellow Mushroom","lat":33.80231,"lng":-84.39314,"kind":"restaurant","cuisine":"pizza"},{"name":"Bell Street Burritos","lat":33.80464,"lng":-84.39376,"kind":"restaurant","cuisine":"mexican"},{"name":"Sufi's Kitchen","lat":33.80442,"lng":-84.3938,"kind":"restaurant","cuisine":"mediterranean"},{"name":"Morton's The Steakhouse","lat":33.76297,"lng":-84.38617,"kind":"restaurant","cuisine":"steak house"},{"name":"Bottle Rocket","lat":33.75005,"lng":-84.40089,"kind":"restaurant","cuisine":"sushi"},{"name":"Match Bar & Oven","lat":33.74947,"lng":-84.40182,"kind":"restaurant","cuisine":"american"},{"name":"Old Lady Gang - A Southern Eatery","lat":33.74966,"lng":-84.39933,"kind":"restaurant","cuisine":"american"},{"name":"Omni Coffee & Eggs","lat":33.74746,"lng":-84.40191,"kind":"restaurant","cuisine":"american"},{"name":"255 Tapas Lounge","lat":33.74768,"lng":-84.40167,"kind":"restaurant","cuisine":"tapas"},{"name":"Frost Bistro & Bar","lat":33.74708,"lng":-84.40254,"kind":"restaurant","cuisine":"american"},{"name":"The Projects Restaurant And Lounge","lat":33.7473,"lng":-84.40155,"kind":"restaurant","cuisine":"american"},{"name":"Esco Restaurant and Tapas","lat":33.74582,"lng":-84.40377,"kind":"restaurant","cuisine":"american"},{"name":"CZ Smokez BBQ","lat":33.74561,"lng":-84.40555,"kind":"restaurant","cuisine":"barbecue"},{"name":"Tyde Tate Kitchen","lat":33.75224,"lng":-84.39517,"kind":"restaurant","cuisine":"thai"},{"name":"El Viñedo Local","lat":33.77438,"lng":-84.38495,"kind":"restaurant","cuisine":"South American"},{"name":"Snooze","lat":33.88108,"lng":-84.4615,"kind":"restaurant","cuisine":"breakfast"},{"name":"Atwoods","lat":33.77744,"lng":-84.38704,"kind":"restaurant","cuisine":"pizza"},{"name":"Three Peaches Gelato and Coffee","lat":33.78143,"lng":-84.36845,"kind":"cafe","cuisine":"coffee shop"},{"name":"Bench Warmers","lat":33.77544,"lng":-84.2995,"kind":"restaurant","cuisine":"american"},{"name":"Sheba Restaurant & Lounge","lat":33.82798,"lng":-84.32652,"kind":"restaurant","cuisine":"american"},{"name":"Starbucks","lat":33.72276,"lng":-84.50704,"kind":"cafe","cuisine":"coffee shop"},{"name":"High Velocity","lat":33.76132,"lng":-84.38508,"kind":"restaurant","cuisine":"american"},{"name":"Starbucks","lat":33.76182,"lng":-84.38508,"kind":"cafe","cuisine":"coffee shop"},{"name":"Atalian Kitchen & Bar","lat":33.75998,"lng":-84.38592,"kind":"restaurant","cuisine":"italian"},{"name":"H&F Burger","lat":33.77285,"lng":-84.36561,"kind":"restaurant","cuisine":"burger"},{"name":"Costa","lat":33.86979,"lng":-84.33621,"kind":"cafe","cuisine":"coffee shop"},{"name":"La Fonda Latina","lat":33.8758,"lng":-84.38003,"kind":"restaurant","cuisine":"mexican"},{"name":"Fellini's Pizza","lat":33.87605,"lng":-84.38,"kind":"restaurant","cuisine":"pizza"},{"name":"Sean's Candler Park","lat":33.76496,"lng":-84.34186,"kind":"cafe","cuisine":"coffee shop"},{"name":"Bellwood Coffee","lat":33.81025,"lng":-84.47691,"kind":"cafe","cuisine":"coffee shop"},{"name":"Your Pie","lat":33.65903,"lng":-84.41947,"kind":"restaurant","cuisine":"pizza"},{"name":"Capolinea","lat":33.75866,"lng":-84.4004,"kind":"restaurant","cuisine":"american"},{"name":"Tin Lizzy's","lat":33.75981,"lng":-84.38668,"kind":"restaurant","cuisine":"tex-mex"},{"name":"Gibney's Pub","lat":33.76036,"lng":-84.38623,"kind":"restaurant","cuisine":"american"},{"name":"Polaris","lat":33.76149,"lng":-84.38681,"kind":"restaurant","cuisine":"american"},{"name":"Taste of Greece","lat":33.77421,"lng":-84.38449,"kind":"restaurant","cuisine":"greek"},{"name":"Egg Harbor Cafe","lat":33.80514,"lng":-84.39405,"kind":"restaurant","cuisine":"american"},{"name":"Osha Thai Sushi Galleria","lat":33.80492,"lng":-84.39398,"kind":"restaurant","cuisine":"asian"},{"name":"The Hive Buckhead","lat":33.80544,"lng":-84.39362,"kind":"restaurant","cuisine":"american"},{"name":"Starbucks","lat":33.80591,"lng":-84.39358,"kind":"cafe","cuisine":"coffee shop"},{"name":"Ding Tea","lat":33.78212,"lng":-84.40781,"kind":"cafe","cuisine":"bubble tea"},{"name":"Pielands","lat":33.7823,"lng":-84.35383,"kind":"restaurant","cuisine":"pizza"},{"name":"Starbucks","lat":33.84699,"lng":-84.37024,"kind":"cafe","cuisine":"coffee shop"},{"name":"North Italia","lat":33.84786,"lng":-84.36373,"kind":"restaurant","cuisine":"italian"},{"name":"Corner Bakery","lat":33.84828,"lng":-84.36735,"kind":"cafe","cuisine":"coffee shop"},{"name":"Starbucks","lat":33.78352,"lng":-84.40773,"kind":"cafe","cuisine":"coffee shop"},{"name":"Willy's Mexicana Grill","lat":33.8492,"lng":-84.42821,"kind":"restaurant","cuisine":"tex-mex"},{"name":"Larakin Wine And Coffee","lat":33.78448,"lng":-84.38059,"kind":"cafe","cuisine":"seafood"},{"name":"Livingston Restaurant & Bar","lat":33.77241,"lng":-84.38469,"kind":"restaurant","cuisine":"american"},{"name":"The Ponce Room Bar & Kitchen","lat":33.77213,"lng":-84.38513,"kind":"restaurant","cuisine":"american"},{"name":"Cafe Sunflower Chinese Cuisine & Sushi","lat":33.77016,"lng":-84.38492,"kind":"restaurant","cuisine":"chinese"},{"name":"Flavor Rich Restaurant","lat":33.76942,"lng":-84.38499,"kind":"restaurant","cuisine":"american"},{"name":"Nikolai's Roof","lat":33.76135,"lng":-84.38307,"kind":"restaurant","cuisine":"european"},{"name":"Foxtail Coffee Co.","lat":33.84895,"lng":-84.37447,"kind":"cafe","cuisine":"coffee shop"},{"name":"Humble Pie","lat":33.78495,"lng":-84.41152,"kind":"restaurant","cuisine":"pizza"},{"name":"Upbeet","lat":33.78422,"lng":-84.41161,"kind":"restaurant","cuisine":"american"},{"name":"Snooze","lat":33.78134,"lng":-84.41128,"kind":"restaurant","cuisine":"breakfast"},{"name":"LTH","lat":33.77091,"lng":-84.36916,"kind":"cafe","cuisine":"coffee shop"},{"name":"Ssamjang","lat":33.88049,"lng":-84.46777,"kind":"restaurant","cuisine":"korean"},{"name":"Starbucks","lat":33.75544,"lng":-84.38212,"kind":"cafe","cuisine":"coffee shop"},{"name":"The Flying Biscuit","lat":33.76288,"lng":-84.33752,"kind":"restaurant","cuisine":"southern"},{"name":"Marcel","lat":33.78568,"lng":-84.41261,"kind":"restaurant","cuisine":"french"},{"name":"v12 Restaurant","lat":33.77067,"lng":-84.38917,"kind":"restaurant","cuisine":"american"},{"name":"Yard House","lat":33.79472,"lng":-84.40539,"kind":"restaurant","cuisine":"american"},{"name":"Spiller Park Specialty Coffee","lat":33.75231,"lng":-84.39529,"kind":"cafe","cuisine":"coffee shop"},{"name":"Sugar Factory","lat":33.78338,"lng":-84.38402,"kind":"restaurant","cuisine":"american"},{"name":"Silverlake Ramen","lat":33.78341,"lng":-84.38422,"kind":"restaurant","cuisine":"ramen"},{"name":"King Springs Chinese Restaurant","lat":33.86197,"lng":-84.51788,"kind":"restaurant","cuisine":"chinese"},{"name":"Johnny Rockets","lat":33.7617,"lng":-84.39502,"kind":"restaurant","cuisine":"american"},{"name":"Dancing Goats Coffee","lat":33.77375,"lng":-84.39857,"kind":"cafe","cuisine":"coffee shop"},{"name":"Edgar's Proof & Provision","lat":33.77245,"lng":-84.3844,"kind":"restaurant","cuisine":"american"},{"name":"683 Midtown Bar and Bistro","lat":33.77315,"lng":-84.38462,"kind":"restaurant","cuisine":"american"},{"name":"Lyla Lila","lat":33.77357,"lng":-84.38462,"kind":"restaurant","cuisine":"italian"},{"name":"Belly Restaurant & Lounge","lat":33.77384,"lng":-84.38496,"kind":"restaurant","cuisine":"american"},{"name":"Land Of A Thousand Hills Coffee & Bar","lat":33.77409,"lng":-84.3845,"kind":"cafe","cuisine":"coffee shop"},{"name":"Buffalo Bayou Coffee","lat":33.77273,"lng":-84.38467,"kind":"cafe","cuisine":"coffee shop"},{"name":"Boone's","lat":33.81496,"lng":-84.40563,"kind":"restaurant","cuisine":"american"},{"name":"Taste On Pine","lat":33.76759,"lng":-84.38252,"kind":"restaurant","cuisine":"american"},{"name":"Za'Acai Cafe","lat":33.77063,"lng":-84.38213,"kind":"restaurant","cuisine":"açaí"},{"name":"Café 30a","lat":33.76447,"lng":-84.3883,"kind":"restaurant","cuisine":"american"},{"name":"Masti Fun Indian Street Eats","lat":33.77833,"lng":-84.38529,"kind":"restaurant","cuisine":"indian"},{"name":"Starbucks","lat":33.77841,"lng":-84.38414,"kind":"cafe","cuisine":"coffee shop"},{"name":"The Melting Pot","lat":33.7753,"lng":-84.38481,"kind":"restaurant","cuisine":"fondue"},{"name":"El Valle Kitchen And Bar","lat":33.77628,"lng":-84.38469,"kind":"restaurant","cuisine":"mexican"},{"name":"Bar Vegan","lat":33.77282,"lng":-84.3659,"kind":"restaurant","cuisine":"american"},{"name":"Grits & Eggs Breakfast Kitchen","lat":33.77376,"lng":-84.38867,"kind":"restaurant","cuisine":"american"},{"name":"Cafe Xpress","lat":33.77528,"lng":-84.38633,"kind":"restaurant","cuisine":"american"},{"name":"Brewdog","lat":33.7561,"lng":-84.36483,"kind":"restaurant","cuisine":"american"},{"name":"Saigon Cafe Smyrna","lat":33.88696,"lng":-84.47556,"kind":"restaurant","cuisine":"vietnamese"},{"name":"Sweet Georgia's Juke Joint","lat":33.75868,"lng":-84.38777,"kind":"restaurant","cuisine":"american"},{"name":"Terrace Bistro & Lounge","lat":33.75819,"lng":-84.38779,"kind":"restaurant","cuisine":"american"},{"name":"Hsu's Gourmet Chinese Restaurant","lat":33.75955,"lng":-84.38623,"kind":"restaurant","cuisine":"chinese"},{"name":"The Crazy Cities!","lat":33.75931,"lng":-84.38438,"kind":"restaurant","cuisine":"american"},{"name":"Fandangles","lat":33.75892,"lng":-84.38381,"kind":"restaurant","cuisine":"american"},{"name":"Collage","lat":33.75877,"lng":-84.38381,"kind":"restaurant","cuisine":"american"},{"name":"Thai Chili","lat":33.81691,"lng":-84.33443,"kind":"restaurant","cuisine":"thai"},{"name":"Sushitto","lat":33.81704,"lng":-84.3344,"kind":"restaurant","cuisine":"sushi"},{"name":"Illy","lat":33.77267,"lng":-84.36391,"kind":"cafe","cuisine":"coffee shop"},{"name":"Bangkok Thai Restaurant","lat":33.79581,"lng":-84.3709,"kind":"restaurant","cuisine":"thai"},{"name":"Morelli's","lat":33.78195,"lng":-84.35445,"kind":"restaurant","cuisine":"ice cream"},{"name":"Press & Grind","lat":33.78173,"lng":-84.35426,"kind":"restaurant","cuisine":"coffee shop"},{"name":"Fitlife Foods","lat":33.85507,"lng":-84.38195,"kind":"restaurant","cuisine":"italian"},{"name":"Rreal Tacos","lat":33.77353,"lng":-84.29545,"kind":"restaurant","cuisine":"mexican"},{"name":"Casa Balam","lat":33.77576,"lng":-84.29866,"kind":"restaurant","cuisine":"mexican"},{"name":"Lloyds Pizza Parlor","lat":33.75488,"lng":-84.35796,"kind":"restaurant","cuisine":"pizza"},{"name":"Local Three Kitchen & Bar","lat":33.84485,"lng":-84.42673,"kind":"restaurant","cuisine":"american"},{"name":"Homespun","lat":33.75889,"lng":-84.40096,"kind":"restaurant","cuisine":"breakfast"},{"name":"Starbucks","lat":33.77042,"lng":-84.38534,"kind":"cafe","cuisine":"coffee shop"},{"name":"Taqueria El Vecino","lat":33.82386,"lng":-84.29406,"kind":"restaurant","cuisine":"mexican"},{"name":"The Grove","lat":33.82431,"lng":-84.29349,"kind":"restaurant","cuisine":"american"},{"name":"Spiller Park Coffee \"SP3\"","lat":33.81932,"lng":-84.44981,"kind":"cafe","cuisine":"coffee shop"},{"name":"Yumbii @Moores Mill","lat":33.81975,"lng":-84.44947,"kind":"restaurant","cuisine":"mexican"},{"name":"Carniceria Ramirez","lat":33.82061,"lng":-84.45001,"kind":"restaurant","cuisine":"mexican"},{"name":"Divan Restaurant & Bar","lat":33.7882,"lng":-84.38474,"kind":"restaurant","cuisine":"mediterranean"},{"name":"Boqueria","lat":33.788,"lng":-84.38333,"kind":"restaurant","cuisine":"spanish"},{"name":"Saints + Council","lat":33.7881,"lng":-84.38301,"kind":"restaurant","cuisine":"steak house"},{"name":"Holeman And Finch Public House","lat":33.7879,"lng":-84.38306,"kind":"restaurant","cuisine":"american"},{"name":"Serena Pastifico","lat":33.78756,"lng":-84.3823,"kind":"restaurant","cuisine":"italian"},{"name":"Brown Bag Seafood Co.","lat":33.78751,"lng":-84.38317,"kind":"restaurant","cuisine":"seafood"},{"name":"J's Taqueria","lat":33.8836,"lng":-84.47802,"kind":"restaurant","cuisine":"mexican"},{"name":"Opo Coffee","lat":33.77191,"lng":-84.29214,"kind":"cafe","cuisine":"coffee shop"},{"name":"Figo Pasta","lat":33.81196,"lng":-84.42631,"kind":"restaurant","cuisine":"pasta"},{"name":"LowCountry Steak","lat":33.78169,"lng":-84.38814,"kind":"restaurant","cuisine":"steak house"},{"name":"Xi'an Gourmet House","lat":33.78131,"lng":-84.38858,"kind":"restaurant","cuisine":"noodle"},{"name":"Nagomiya","lat":33.7817,"lng":-84.38841,"kind":"restaurant","cuisine":"japanese"},{"name":"Sway Restaurant","lat":33.76186,"lng":-84.38688,"kind":"restaurant","cuisine":"american"},{"name":"Lobby Market","lat":33.76184,"lng":-84.38651,"kind":"cafe","cuisine":"coffee shop"},{"name":"Cafe Fwi","lat":33.76082,"lng":-84.38794,"kind":"cafe","cuisine":"coffee shop"},{"name":"Cafe Momentum","lat":33.75904,"lng":-84.38776,"kind":"restaurant","cuisine":"american"},{"name":"Rumi's Kitchen","lat":33.78683,"lng":-84.38304,"kind":"restaurant","cuisine":"persian"},{"name":"Brasserie Margot","lat":33.78638,"lng":-84.3852,"kind":"restaurant","cuisine":"french"},{"name":"Carolyn's Gourmet Cafe","lat":33.78695,"lng":-84.38727,"kind":"restaurant","cuisine":"american"},{"name":"Fin & Feathers Midtown","lat":33.78578,"lng":-84.38435,"kind":"restaurant","cuisine":"american"},{"name":"Emilio's Tacos & Tequila","lat":33.78542,"lng":-84.38647,"kind":"restaurant","cuisine":"mexican"},{"name":"McCray's Tavern","lat":33.78591,"lng":-84.38763,"kind":"restaurant","cuisine":"american"},{"name":"Foxtail Coffee Co.","lat":33.78815,"lng":-84.38802,"kind":"cafe","cuisine":"coffee shop"},{"name":"Toastique","lat":33.78801,"lng":-84.38803,"kind":"cafe","cuisine":"american"},{"name":"Tin Lizzy's Taco Americana","lat":33.7844,"lng":-84.38457,"kind":"restaurant","cuisine":"mexican"},{"name":"Tower Market","lat":33.78787,"lng":-84.385,"kind":"cafe","cuisine":"american"},{"name":"The Companion","lat":33.8185,"lng":-84.4621,"kind":"restaurant","cuisine":"american"},{"name":"Little Rey","lat":33.85561,"lng":-84.4291,"kind":"restaurant","cuisine":"mexican"},{"name":"The Daily","lat":33.85522,"lng":-84.42955,"kind":"cafe","cuisine":"coffee shop"},{"name":"Sushi Tong","lat":33.86561,"lng":-84.492,"kind":"restaurant","cuisine":"sushi"},{"name":"Arden's Garden Juice Bar & Smoothies West Midtown","lat":33.77892,"lng":-84.40938,"kind":"cafe","cuisine":"juice"},{"name":"MetroFresh Uptown","lat":33.79174,"lng":-84.38629,"kind":"cafe","cuisine":"sandwich"},{"name":"Hartley Kitchen & Cocktails","lat":33.79078,"lng":-84.38834,"kind":"restaurant","cuisine":"american"},{"name":"Pom Court","lat":33.79007,"lng":-84.38834,"kind":"restaurant","cuisine":"spanish"},{"name":"Krave Korean Grill","lat":33.81093,"lng":-84.42576,"kind":"restaurant","cuisine":"korean"},{"name":"Starbucks","lat":33.8378,"lng":-84.31253,"kind":"cafe","cuisine":"coffee shop"},{"name":"The Bean Counter","lat":33.78774,"lng":-84.38515,"kind":"cafe","cuisine":"coffee shop"},{"name":"Yami Sushi","lat":33.78997,"lng":-84.30777,"kind":"restaurant","cuisine":"sushi"},{"name":"Savi Provisions","lat":33.78095,"lng":-84.38426,"kind":"cafe","cuisine":"sandwich"},{"name":"26 Thai Kitchen & Bar","lat":33.77701,"lng":-84.38304,"kind":"restaurant","cuisine":"thai"},{"name":"Sebastián Pintxos Bar","lat":33.77688,"lng":-84.38308,"kind":"restaurant","cuisine":"spanish"},{"name":"Alta Toro Modern Latin","lat":33.78055,"lng":-84.38714,"kind":"restaurant","cuisine":"spanish"},{"name":"Café Intermezzo","lat":33.78332,"lng":-84.38365,"kind":"cafe","cuisine":"coffee shop"},{"name":"Nancy's Pizza Midtown","lat":33.77237,"lng":-84.3789,"kind":"restaurant","cuisine":"pizza"},{"name":"Wok Chi Asian Kitchen","lat":33.77393,"lng":-84.40573,"kind":"restaurant","cuisine":"asian"},{"name":"Capital Commons","lat":33.78646,"lng":-84.38848,"kind":"cafe","cuisine":"coffee shop"},{"name":"The Flying Biscuit Cafe","lat":33.8103,"lng":-84.41553,"kind":"restaurant","cuisine":"american"},{"name":"Crescent City Kitchen","lat":33.78381,"lng":-84.38436,"kind":"restaurant","cuisine":"american"},{"name":"Dua Vietnamese","lat":33.7842,"lng":-84.3846,"kind":"restaurant","cuisine":"vietnamese"},{"name":"Tabla Indian Cuisine","lat":33.78441,"lng":-84.38518,"kind":"restaurant","cuisine":"indian"},{"name":"Dos Caminos","lat":33.78452,"lng":-84.38326,"kind":"restaurant","cuisine":"mexican"},{"name":"STK Steakhouse","lat":33.78418,"lng":-84.38293,"kind":"restaurant","cuisine":"steak house"},{"name":"Momonoki Momo Cafe","lat":33.77974,"lng":-84.39034,"kind":"restaurant","cuisine":"japanese"},{"name":"Forza Storico","lat":33.78663,"lng":-84.41214,"kind":"restaurant","cuisine":"italian"},{"name":"The Consulate","lat":33.78184,"lng":-84.38661,"kind":"restaurant","cuisine":"international"},{"name":"El Santo Gallo","lat":33.78337,"lng":-84.4189,"kind":"restaurant","cuisine":"mexican"},{"name":"Tuza Taco","lat":33.79681,"lng":-84.4158,"kind":"restaurant","cuisine":"mexican"},{"name":"5Church Buckhead","lat":33.84786,"lng":-84.36582,"kind":"restaurant","cuisine":"american"},{"name":"Bezoria","lat":33.88047,"lng":-84.46734,"kind":"restaurant","cuisine":"middle eastern"},{"name":"J Christopher's","lat":33.77998,"lng":-84.38751,"kind":"restaurant","cuisine":"american"},{"name":"Marlow's Tavern","lat":33.77972,"lng":-84.38751,"kind":"restaurant","cuisine":"american"},{"name":"Ashland","lat":33.78319,"lng":-84.3831,"kind":"restaurant","cuisine":"japanese"},{"name":"For Five Coffee Roasters","lat":33.78494,"lng":-84.3876,"kind":"cafe","cuisine":"coffee shop"},{"name":"E Ramen +","lat":33.78511,"lng":-84.38802,"kind":"restaurant","cuisine":"ramen"},{"name":"Land Of A Thousand Hills Coffee","lat":33.78552,"lng":-84.38944,"kind":"cafe","cuisine":"coffee shop"},{"name":"The Sparrow","lat":33.77982,"lng":-84.3875,"kind":"restaurant","cuisine":"chinese"},{"name":"Hudson Grille","lat":33.78039,"lng":-84.38433,"kind":"restaurant","cuisine":"american"},{"name":"Agora Mediterranean Cuisine","lat":33.78095,"lng":-84.3845,"kind":"restaurant","cuisine":"mediterranean"},{"name":"Lazy Betty","lat":33.78134,"lng":-84.38372,"kind":"restaurant","cuisine":"american"},{"name":"Perc","lat":33.75123,"lng":-84.3094,"kind":"cafe","cuisine":"coffee shop"},{"name":"T's Brunch Bar","lat":33.77977,"lng":-84.38402,"kind":"restaurant","cuisine":"american"},{"name":"La Santa Tacos & Bar","lat":33.77936,"lng":-84.38247,"kind":"restaurant","cuisine":"mexican"},{"name":"Triple Jays Pizza Bar","lat":33.78257,"lng":-84.38044,"kind":"restaurant","cuisine":"pizza"},{"name":"Bar Of Thailand","lat":33.78284,"lng":-84.38035,"kind":"restaurant","cuisine":"thai"},{"name":"Desi Spice Indian Cuisine","lat":33.77934,"lng":-84.36736,"kind":"restaurant","cuisine":"indian"},{"name":"Tiki Thai","lat":33.80125,"lng":-84.41359,"kind":"restaurant","cuisine":"thai"},{"name":"Bao Bun Hibachi","lat":33.80123,"lng":-84.41344,"kind":"restaurant","cuisine":"taiwanese"},{"name":"Discourse Eatery","lat":33.79255,"lng":-84.38598,"kind":"restaurant","cuisine":"american"},{"name":"Ninja Way Express","lat":33.79245,"lng":-84.38592,"kind":"restaurant","cuisine":"sushi"},{"name":"Foxtail Coffee Co.","lat":33.77721,"lng":-84.38375,"kind":"cafe","cuisine":"coffee shop"},{"name":"Spiller Park Coffee","lat":33.78087,"lng":-84.38394,"kind":"cafe","cuisine":"coffee shop"},{"name":"Howell's Kitchen & Bar","lat":33.80837,"lng":-84.41298,"kind":"restaurant","cuisine":"american"},{"name":"Guru Revolving Sushi","lat":33.77939,"lng":-84.38404,"kind":"restaurant","cuisine":"sushi"},{"name":"Big Bad Breakfast","lat":33.80793,"lng":-84.41294,"kind":"restaurant","cuisine":"american"},{"name":"Noodoh Asian Fusion & Bar","lat":33.76875,"lng":-84.3832,"kind":"restaurant","cuisine":"asian"},{"name":"Mo's Pizza","lat":33.83716,"lng":-84.3105,"kind":"restaurant","cuisine":"pizza"},{"name":"Hudson & Alphonse","lat":33.71786,"lng":-84.37895,"kind":"restaurant","cuisine":"sandwich"},{"name":"Cuevacia","lat":33.78742,"lng":-84.38306,"kind":"restaurant","cuisine":"mexican"},{"name":"Restaurant Ten Bar And Grill","lat":33.75394,"lng":-84.40279,"kind":"restaurant","cuisine":"american"},{"name":"Wadada Healthy Market & Juice Bar","lat":33.738,"lng":-84.41651,"kind":"restaurant","cuisine":"juice"},{"name":"The Colonnade Restaurant","lat":33.80933,"lng":-84.36101,"kind":"restaurant","cuisine":"american"},{"name":"The Food Shoppe","lat":33.75828,"lng":-84.39041,"kind":"restaurant","cuisine":"creole"},{"name":"Cultured South","lat":33.73192,"lng":-84.42208,"kind":"restaurant","cuisine":"sandwich"},{"name":"Hibachiman","lat":33.83898,"lng":-84.48107,"kind":"restaurant","cuisine":"japanese"},{"name":"Schāf Shop","lat":33.77915,"lng":-84.38248,"kind":"cafe","cuisine":"coffee shop"},{"name":"Bird & Batter","lat":33.75961,"lng":-84.37188,"kind":"restaurant","cuisine":"american"},{"name":"Amistad Coffee","lat":33.7892,"lng":-84.38798,"kind":"cafe","cuisine":"coffee shop"},{"name":"Crispina Ristorante & Pizzeria","lat":33.87268,"lng":-84.45752,"kind":"restaurant","cuisine":"pizza"},{"name":"Vinny's N.Y. Pizza & Grill - Piedmont","lat":33.79801,"lng":-84.37066,"kind":"restaurant","cuisine":"pizza"},{"name":"Baraka Shawarma Mediterranean Cuisine","lat":33.75646,"lng":-84.39106,"kind":"restaurant","cuisine":"shawarma"},{"name":"Gio's Sicilian","lat":33.78496,"lng":-84.40575,"kind":"restaurant","cuisine":"pizza"},{"name":"Gold and Bold","lat":33.77864,"lng":-84.39722,"kind":"cafe","cuisine":"coffee shop"},{"name":"Tea Leaf and Creamery","lat":33.77712,"lng":-84.38925,"kind":"cafe","cuisine":"bubble tea"},{"name":"Möge Tee","lat":33.78185,"lng":-84.40463,"kind":"cafe","cuisine":"bubble tea"},{"name":"alonetogether","lat":33.78928,"lng":-84.38798,"kind":"restaurant","cuisine":"hatian"},{"name":"Souper Jenny","lat":33.79081,"lng":-84.30536,"kind":"restaurant","cuisine":"soup"},{"name":"J'ouvert Caribbean Kitchen & Bar","lat":33.82267,"lng":-84.3689,"kind":"restaurant","cuisine":"caribbean"},{"name":"Broad Street BBQ","lat":33.75194,"lng":-84.39304,"kind":"restaurant","cuisine":"barbecue"},{"name":"Brewhouse","lat":33.75212,"lng":-84.39321,"kind":"restaurant","cuisine":"grill"},{"name":"Bottle Rocket","lat":33.75224,"lng":-84.39521,"kind":"restaurant","cuisine":"sushi"},{"name":"Whiskey Bird","lat":33.79269,"lng":-84.35178,"kind":"restaurant","cuisine":"american"},{"name":"Summit Coffee","lat":33.85916,"lng":-84.34022,"kind":"cafe","cuisine":"coffee shop"},{"name":"Bones","lat":33.84176,"lng":-84.37103,"kind":"restaurant","cuisine":"steak house"},{"name":"Revival","lat":33.77165,"lng":-84.29462,"kind":"restaurant","cuisine":"american"},{"name":"Fellini's Pizza","lat":33.77323,"lng":-84.29003,"kind":"restaurant","cuisine":"pizza"},{"name":"Elmyriachi Restaurant & Cantina","lat":33.75253,"lng":-84.32376,"kind":"restaurant","cuisine":"mexican"},{"name":"Dancing Goats Coffee Bar","lat":33.77592,"lng":-84.30325,"kind":"cafe","cuisine":"coffee shop"},{"name":"Fellini's Pizza","lat":33.76499,"lng":-84.33394,"kind":"restaurant","cuisine":"pizza"},{"name":"1911 Biscuits & Burgers","lat":33.87761,"lng":-84.53281,"kind":"restaurant","cuisine":"burger"},{"name":"Monterrey Mexican Restaurant","lat":33.87264,"lng":-84.53048,"kind":"restaurant","cuisine":"mexican"},{"name":"Esco Seafood","lat":33.75416,"lng":-84.37289,"kind":"restaurant","cuisine":"seafood"},{"name":"Edgewood Pizzeria","lat":33.7545,"lng":-84.37197,"kind":"restaurant","cuisine":"pizza"},{"name":"La Hacienda Midtown","lat":33.77917,"lng":-84.36968,"kind":"restaurant","cuisine":"mexican"},{"name":"Mellow Mushroom","lat":33.8162,"lng":-84.33281,"kind":"restaurant","cuisine":"pizza"},{"name":"Waffle House","lat":33.65933,"lng":-84.42922,"kind":"restaurant","cuisine":"american"},{"name":"Tacos & Tequilas Mexican Grill","lat":33.77378,"lng":-84.36685,"kind":"restaurant","cuisine":"mexican"},{"name":"Starbucks","lat":33.77363,"lng":-84.36589,"kind":"cafe","cuisine":"coffee shop"},{"name":"Park Tavern","lat":33.78215,"lng":-84.36928,"kind":"restaurant","cuisine":"american"},{"name":"Starbucks","lat":33.78027,"lng":-84.36884,"kind":"cafe","cuisine":"coffee shop"},{"name":"Waffle House","lat":33.7599,"lng":-84.3918,"kind":"restaurant","cuisine":"american"},{"name":"Applebee's","lat":33.72301,"lng":-84.509,"kind":"restaurant","cuisine":"american"},{"name":"Smoothie King","lat":33.72295,"lng":-84.50826,"kind":"restaurant","cuisine":"smoothie"},{"name":"Fellini's Pizza","lat":33.77351,"lng":-84.35767,"kind":"restaurant","cuisine":"pizza"},{"name":"Flip Burger Boutique","lat":33.77267,"lng":-84.35281,"kind":"restaurant","cuisine":"burger"},{"name":"PERC Atlanta Highlands","lat":33.78321,"lng":-84.35474,"kind":"cafe","cuisine":"coffee shop"},{"name":"IHOP","lat":33.77335,"lng":-84.37337,"kind":"restaurant","cuisine":"breakfast"},{"name":"Jack's Pizza","lat":33.76147,"lng":-84.36518,"kind":"restaurant","cuisine":"pizza"},{"name":"The Albert","lat":33.762,"lng":-84.35752,"kind":"restaurant","cuisine":"american"},{"name":"Fritti","lat":33.76289,"lng":-84.35772,"kind":"restaurant","cuisine":"italian pizza"},{"name":"Casa Almenara","lat":33.78164,"lng":-84.3803,"kind":"restaurant","cuisine":"tulum"},{"name":"Taquiera Del Sol","lat":33.81325,"lng":-84.35355,"kind":"restaurant","cuisine":"taquiera"},{"name":"Mama's Cocina Latina","lat":33.81096,"lng":-84.36707,"kind":"restaurant","cuisine":"mexican"},{"name":"The Original Pancake House","lat":33.81828,"lng":-84.35019,"kind":"restaurant","cuisine":"breakfast"},{"name":"Rain Thai and Sushi Bar","lat":33.8189,"lng":-84.34967,"kind":"restaurant","cuisine":"asian"},{"name":"Hong Kong Harbour","lat":33.81452,"lng":-84.35378,"kind":"restaurant","cuisine":"chinese"},{"name":"Taverna Plaka","lat":33.81483,"lng":-84.35362,"kind":"restaurant","cuisine":"greek"},{"name":"Waffle House","lat":33.81696,"lng":-84.35256,"kind":"restaurant","cuisine":"american"},{"name":"Octopus Kitchen","lat":33.79672,"lng":-84.36901,"kind":"restaurant","cuisine":"american"},{"name":"Fat Matt's Rib Shack","lat":33.80453,"lng":-84.36706,"kind":"restaurant","cuisine":"barbecue"},{"name":"Ghion Cultural Hall","lat":33.8125,"lng":-84.35519,"kind":"restaurant","cuisine":"ethiopian"},{"name":"Nino's Cucina Italiana","lat":33.80996,"lng":-84.35955,"kind":"restaurant","cuisine":"italian"},{"name":"Las Margaritas","lat":33.80945,"lng":-84.36234,"kind":"restaurant","cuisine":"mexican"},{"name":"Johnny's New York Pizza","lat":33.8091,"lng":-84.36357,"kind":"restaurant","cuisine":"pizza"},{"name":"Nakato Japanese Restaurant","lat":33.80871,"lng":-84.36472,"kind":"restaurant","cuisine":"japanese"},{"name":"Atmosphere","lat":33.79883,"lng":-84.36834,"kind":"restaurant","cuisine":"french"},{"name":"The Nook","lat":33.78604,"lng":-84.3785,"kind":"restaurant","cuisine":"american"},{"name":"Genki Noodles & Sushi","lat":33.84216,"lng":-84.37923,"kind":"restaurant","cuisine":"asian"},{"name":"Waffle House","lat":33.84114,"lng":-84.31407,"kind":"restaurant","cuisine":"american"},{"name":"Little Bangkok Thai Cuisine","lat":33.81586,"lng":-84.35225,"kind":"restaurant","cuisine":"thai"},{"name":"LongHorn Steakhouse","lat":33.8217,"lng":-84.36796,"kind":"restaurant","cuisine":"steak house"},{"name":"Zesto Drive-In","lat":33.82294,"lng":-84.36693,"kind":"restaurant","cuisine":"american"},{"name":"Buckhead BBQ","lat":33.84136,"lng":-84.37978,"kind":"restaurant","cuisine":"barbecue"},{"name":"IHOP","lat":33.84066,"lng":-84.37821,"kind":"restaurant","cuisine":"breakfast"},{"name":"Grindhouse Killer Burgers","lat":33.80613,"lng":-84.36737,"kind":"restaurant","cuisine":"burger"},{"name":"Gino's NY Pizza Bar","lat":33.80827,"lng":-84.36552,"kind":"restaurant","cuisine":"pizza"},{"name":"Prime On Peachtree","lat":33.78275,"lng":-84.38364,"kind":"restaurant","cuisine":"steak house"},{"name":"Campagnolo","lat":33.78138,"lng":-84.38094,"kind":"restaurant","cuisine":"italian"},{"name":"Max Lager's","lat":33.76334,"lng":-84.38704,"kind":"restaurant","cuisine":"american"},{"name":"OK Cafe","lat":33.84881,"lng":-84.42944,"kind":"restaurant","cuisine":"regional"},{"name":"Bullpen Rib House","lat":33.73481,"lng":-84.39135,"kind":"restaurant","cuisine":"barbecue"},{"name":"Waffle House","lat":33.8851,"lng":-84.47175,"kind":"restaurant","cuisine":"american"},{"name":"Applebee's","lat":33.88466,"lng":-84.47308,"kind":"restaurant","cuisine":"american"},{"name":"Carabba's Italian Grill","lat":33.88119,"lng":-84.47379,"kind":"restaurant","cuisine":"italian"},{"name":"Wild Roots of India","lat":33.88277,"lng":-84.47815,"kind":"restaurant","cuisine":"indian"},{"name":"Cinco Mexican Cantina","lat":33.88311,"lng":-84.46165,"kind":"restaurant","cuisine":"mexican"},{"name":"Houston's","lat":33.85131,"lng":-84.42997,"kind":"restaurant","cuisine":"american"},{"name":"Blue Ridge Grill","lat":33.84968,"lng":-84.42933,"kind":"restaurant","cuisine":"american"},{"name":"Stake 'n Shake","lat":33.84786,"lng":-84.4302,"kind":"restaurant","cuisine":"diner"},{"name":"Atlanta Fish Market","lat":33.83669,"lng":-84.3788,"kind":"restaurant","cuisine":"seafood"},{"name":"Waffle House","lat":33.85702,"lng":-84.38168,"kind":"restaurant","cuisine":"american"},{"name":"Anis Café & Bistro","lat":33.83577,"lng":-84.37659,"kind":"restaurant","cuisine":"french"},{"name":"Starbucks","lat":33.84616,"lng":-84.37309,"kind":"cafe","cuisine":"coffee shop"},{"name":"Waffle House","lat":33.83735,"lng":-84.36867,"kind":"restaurant","cuisine":"american"},{"name":"Waffle House","lat":33.83092,"lng":-84.34389,"kind":"restaurant","cuisine":"american"},{"name":"Fogo de Chão","lat":33.84065,"lng":-84.36939,"kind":"restaurant","cuisine":"brazilian"},{"name":"The Corner Grille Upper West Side","lat":33.81922,"lng":-84.45205,"kind":"restaurant","cuisine":"american"},{"name":"Fellini's Pizza","lat":33.80918,"lng":-84.41262,"kind":"restaurant","cuisine":"pizza"},{"name":"Houston's","lat":33.81351,"lng":-84.39278,"kind":"restaurant","cuisine":"american"},{"name":"Nuevo Laredo Cantina","lat":33.8095,"lng":-84.43678,"kind":"restaurant","cuisine":"mexican"},{"name":"B's CRACKLIN' BBQ","lat":33.81205,"lng":-84.47211,"kind":"restaurant","cuisine":"barbecue"},{"name":"El Azteca","lat":33.80333,"lng":-84.3935,"kind":"restaurant","cuisine":"mexican"},{"name":"The Daiquiri Factory","lat":33.79835,"lng":-84.41575,"kind":"restaurant","cuisine":"american"},{"name":"Willy's Mexicana Grill","lat":33.80733,"lng":-84.41318,"kind":"restaurant","cuisine":"mexican"},{"name":"The Juicy Crab","lat":33.80115,"lng":-84.41432,"kind":"restaurant","cuisine":"seafood"},{"name":"Waffle House","lat":33.80076,"lng":-84.41626,"kind":"restaurant","cuisine":"american"},{"name":"The Pagoda","lat":33.80682,"lng":-84.36692,"kind":"restaurant","cuisine":"chinese"},{"name":"Negril ATL","lat":33.80069,"lng":-84.42055,"kind":"restaurant","cuisine":"caribbean"},{"name":"Pasta Da Pulcinella","lat":33.78491,"lng":-84.38813,"kind":"restaurant","cuisine":"italian"},{"name":"South City Kitchen","lat":33.786,"lng":-84.38446,"kind":"restaurant","cuisine":"american"},{"name":"Steamhouse Lounge","lat":33.78343,"lng":-84.38748,"kind":"restaurant","cuisine":"seafood"},{"name":"Poor Calvin's","lat":33.76847,"lng":-84.38224,"kind":"restaurant","cuisine":"asian"},{"name":"Cameli's Pizza","lat":33.76369,"lng":-84.34902,"kind":"restaurant","cuisine":"pizza"},{"name":"Atlanta Breakfast Club","lat":33.76496,"lng":-84.39547,"kind":"restaurant","cuisine":"breakfast"},{"name":"Ammazza","lat":33.75407,"lng":-84.36802,"kind":"restaurant","cuisine":"pizza"},{"name":"Dat Fire Jerk Chicken","lat":33.74827,"lng":-84.4047,"kind":"restaurant","cuisine":"caribbean"},{"name":"Rosie's Coffee Café","lat":33.75358,"lng":-84.40247,"kind":"restaurant","cuisine":"breakfast"},{"name":"Homegrown","lat":33.74677,"lng":-84.35594,"kind":"restaurant","cuisine":"breakfast"},{"name":"Muchacho","lat":33.74687,"lng":-84.35799,"kind":"restaurant","cuisine":"mexican"},{"name":"Daddy D'z","lat":33.74711,"lng":-84.37899,"kind":"restaurant","cuisine":"barbecue"},{"name":"Mezcalito's","lat":33.74637,"lng":-84.37466,"kind":"restaurant","cuisine":"mexican"},{"name":"The Ke'nekt Cooperative","lat":33.7423,"lng":-84.43705,"kind":"cafe","cuisine":"coffee shop"},{"name":"Argosy","lat":33.74133,"lng":-84.34622,"kind":"restaurant","cuisine":"american"},{"name":"Pollo Primo","lat":33.73278,"lng":-84.34894,"kind":"restaurant","cuisine":"chicken"},{"name":"Zesto","lat":33.72383,"lng":-84.34976,"kind":"restaurant","cuisine":"chicken"},{"name":"American Deli","lat":33.68199,"lng":-84.40805,"kind":"restaurant","cuisine":"american"},{"name":"Waffle House","lat":33.67527,"lng":-84.44364,"kind":"restaurant","cuisine":"american"},{"name":"Spondivits","lat":33.6592,"lng":-84.42905,"kind":"restaurant","cuisine":"seafood"},{"name":"Ruby Tuesday","lat":33.6586,"lng":-84.4294,"kind":"restaurant","cuisine":"american"},{"name":"Waffle House","lat":33.65922,"lng":-84.41675,"kind":"restaurant","cuisine":"american"},{"name":"Barbecue Kitchen","lat":33.65958,"lng":-84.43613,"kind":"restaurant","cuisine":"barbecue"},{"name":"Happy Buddha","lat":33.65961,"lng":-84.4369,"kind":"restaurant","cuisine":"chinese"},{"name":"Golden Panda Buffet","lat":33.76603,"lng":-84.53011,"kind":"restaurant","cuisine":"chinese"},{"name":"Waffle House","lat":33.76429,"lng":-84.53092,"kind":"restaurant","cuisine":"american"},{"name":"American Deli","lat":33.65503,"lng":-84.50495,"kind":"restaurant","cuisine":"american"},{"name":"Chili's","lat":33.65492,"lng":-84.50795,"kind":"restaurant","cuisine":"tex-mex"},{"name":"TGI Friday's","lat":33.65505,"lng":-84.50871,"kind":"restaurant","cuisine":"american"},{"name":"Jason's Deli","lat":33.65583,"lng":-84.50916,"kind":"restaurant","cuisine":"sandwich"},{"name":"LongHorn Steakhouse","lat":33.6559,"lng":-84.50288,"kind":"restaurant","cuisine":"steak house"},{"name":"Olive Garden","lat":33.65683,"lng":-84.50067,"kind":"restaurant","cuisine":"italian"},{"name":"Red Lobster","lat":33.65701,"lng":-84.50001,"kind":"restaurant","cuisine":"seafood"},{"name":"Chili's","lat":33.65723,"lng":-84.49919,"kind":"restaurant","cuisine":"tex-mex"},{"name":"Starbucks","lat":33.84423,"lng":-84.48988,"kind":"cafe","cuisine":"coffee shop"},{"name":"Jim 'N Nick's Bar-B-Q","lat":33.84218,"lng":-84.50017,"kind":"restaurant","cuisine":"barbecue"},{"name":"Starbuck's","lat":33.86488,"lng":-84.47746,"kind":"cafe","cuisine":"coffee shop"},{"name":"Waffle House","lat":33.84053,"lng":-84.51934,"kind":"restaurant","cuisine":"american"},{"name":"Stone Soup Kitchen","lat":33.74564,"lng":-84.36841,"kind":"restaurant","cuisine":"american"},{"name":"Kimball House","lat":33.7716,"lng":-84.29227,"kind":"restaurant","cuisine":"upscale"},{"name":"CAVA","lat":33.8813,"lng":-84.46315,"kind":"restaurant","cuisine":"mediterranean"},{"name":"Copeland's","lat":33.87744,"lng":-84.45587,"kind":"restaurant","cuisine":"american"},{"name":"Stockyard Burgers and Bones","lat":33.86546,"lng":-84.46884,"kind":"restaurant","cuisine":"barbecue"},{"name":"Figo","lat":33.86643,"lng":-84.46715,"kind":"restaurant","cuisine":"italian"},{"name":"Hong Kong Super Buffet","lat":33.77558,"lng":-84.56107,"kind":"restaurant","cuisine":"chinese"},{"name":"Sweet Auburn BBQ","lat":33.7723,"lng":-84.35271,"kind":"restaurant","cuisine":"barbecue"},{"name":"Soul Vegan","lat":33.77221,"lng":-84.35271,"kind":"restaurant","cuisine":"soul"},{"name":"Fellini's Pizza","lat":33.82558,"lng":-84.29119,"kind":"restaurant","cuisine":"pizza"},{"name":"Foxx Jamaican","lat":33.75449,"lng":-84.37528,"kind":"restaurant","cuisine":"jamaican"},{"name":"Cluck 'n Moo","lat":33.77951,"lng":-84.4054,"kind":"restaurant","cuisine":"burger"},{"name":"CAFE + VELO","lat":33.7542,"lng":-84.37501,"kind":"cafe","cuisine":"coffee shop"},{"name":"Venkman's","lat":33.76682,"lng":-84.36326,"kind":"restaurant","cuisine":"american"},{"name":"Beatlecat","lat":33.76265,"lng":-84.35824,"kind":"restaurant","cuisine":"seafood"},{"name":"Bartaco","lat":33.76244,"lng":-84.35858,"kind":"restaurant","cuisine":"tacos"},{"name":"Char","lat":33.76217,"lng":-84.35907,"kind":"restaurant","cuisine":"korean"},{"name":"La Fiesta Mexican Grille and Bar","lat":33.6596,"lng":-84.43533,"kind":"restaurant","cuisine":"mexican"},{"name":"Bonefish Grill","lat":33.88014,"lng":-84.45895,"kind":"restaurant","cuisine":"seafood"},{"name":"Dixie-Q","lat":33.86129,"lng":-84.33229,"kind":"restaurant","cuisine":"barbecue"},{"name":"Waffle House","lat":33.79856,"lng":-84.5128,"kind":"restaurant","cuisine":"american"},{"name":"Zoya Mediterranean Kitchen","lat":33.87628,"lng":-84.52331,"kind":"restaurant","cuisine":"greek"},{"name":"IHOP","lat":33.83684,"lng":-84.31111,"kind":"restaurant","cuisine":"breakfast"},{"name":"McAlister's Deli","lat":33.79085,"lng":-84.40744,"kind":"restaurant","cuisine":"sandwich"},{"name":"Grindhouse Killer Burgers","lat":33.7726,"lng":-84.29628,"kind":"restaurant","cuisine":"american"},{"name":"Waffle House","lat":33.74075,"lng":-84.36184,"kind":"restaurant","cuisine":"american"},{"name":"Mediterranea","lat":33.73164,"lng":-84.37684,"kind":"restaurant","cuisine":"mediterranean"},{"name":"Patria Cocina","lat":33.72556,"lng":-84.37704,"kind":"restaurant","cuisine":"mexican"},{"name":"Hotto Hotto Ramen & Teppanyaki","lat":33.72583,"lng":-84.37704,"kind":"restaurant","cuisine":"japanese"},{"name":"Pizza Hut","lat":33.81157,"lng":-84.47613,"kind":"restaurant","cuisine":"pizza"},{"name":"Waffle House","lat":33.81074,"lng":-84.47541,"kind":"restaurant","cuisine":"american"},{"name":"Sabores","lat":33.81283,"lng":-84.56082,"kind":"cafe","cuisine":"caribbean"},{"name":"Chattahoochee Coffee Company","lat":33.80185,"lng":-84.50258,"kind":"cafe","cuisine":"coffee shop"},{"name":"Star Provisions","lat":33.79485,"lng":-84.42727,"kind":"restaurant","cuisine":"coffee shop"},{"name":"Junior's Pizza","lat":33.73654,"lng":-84.38538,"kind":"restaurant","cuisine":"pizza"},{"name":"Starbucks","lat":33.81618,"lng":-84.33464,"kind":"cafe","cuisine":"coffee shop"},{"name":"Waffle House","lat":33.82561,"lng":-84.36602,"kind":"restaurant","cuisine":"american"},{"name":"Slice Downtown","lat":33.75692,"lng":-84.39003,"kind":"restaurant","cuisine":"pizza"},{"name":"Hard Rock Cafe","lat":33.75993,"lng":-84.38716,"kind":"restaurant","cuisine":"american"},{"name":"Blaze Pizza","lat":33.79104,"lng":-84.407,"kind":"restaurant","cuisine":"pizza"},{"name":"Mamoun's Falafel","lat":33.79013,"lng":-84.40739,"kind":"restaurant","cuisine":"falafel"},{"name":"Nan Thai Fine Dining","lat":33.79158,"lng":-84.38954,"kind":"restaurant","cuisine":"thai"},{"name":"New Realm Brewing","lat":33.76903,"lng":-84.36195,"kind":"restaurant","cuisine":"american"},{"name":"Waffle House","lat":33.78468,"lng":-84.40707,"kind":"restaurant","cuisine":"american"},{"name":"Maggiano's Little Italy","lat":33.88086,"lng":-84.46773,"kind":"restaurant","cuisine":"italian"},{"name":"The Cheesecake Factory","lat":33.88082,"lng":-84.46815,"kind":"restaurant","cuisine":"american"},{"name":"P.F. Chang's","lat":33.88103,"lng":-84.46862,"kind":"restaurant","cuisine":"asian"},{"name":"Buffalo Wild Wings","lat":33.88118,"lng":-84.46879,"kind":"restaurant","cuisine":"wings"},{"name":"Stoney River","lat":33.88144,"lng":-84.46919,"kind":"restaurant","cuisine":"steak house"},{"name":"Bolivar Cafe","lat":33.84382,"lng":-84.50337,"kind":"cafe","cuisine":"coffee shop"},{"name":"Pizza Hut","lat":33.84367,"lng":-84.5037,"kind":"restaurant","cuisine":"pizza"},{"name":"US Cafe","lat":33.84518,"lng":-84.50113,"kind":"restaurant","cuisine":"burger"},{"name":"Grand Champion BBQ","lat":33.80175,"lng":-84.50237,"kind":"restaurant","cuisine":"barbecue"},{"name":"Waffle House","lat":33.84483,"lng":-84.49083,"kind":"restaurant","cuisine":"american"},{"name":"Tokyo Sushi","lat":33.84175,"lng":-84.50574,"kind":"restaurant","cuisine":"sushi"},{"name":"Luna Maya Mexican Restaurant","lat":33.84206,"lng":-84.50161,"kind":"restaurant","cuisine":"mexican"},{"name":"Twisted Kitchen","lat":33.84285,"lng":-84.50085,"kind":"restaurant","cuisine":"asian"},{"name":"Sushinobo in Vinings","lat":33.84404,"lng":-84.49076,"kind":"restaurant","cuisine":"sushi"},{"name":"L'Thai Organic Cafe & Wine Bar","lat":33.84342,"lng":-84.49053,"kind":"restaurant","cuisine":"thai"},{"name":"Fellini's Pizza","lat":33.83156,"lng":-84.38498,"kind":"restaurant","cuisine":"pizza"},{"name":"Starbucks","lat":33.87861,"lng":-84.38018,"kind":"cafe","cuisine":"coffee shop"},{"name":"Roasters Rotisserie","lat":33.83108,"lng":-84.35662,"kind":"restaurant","cuisine":"chicken"},{"name":"Nova Sushi","lat":33.85276,"lng":-84.35846,"kind":"restaurant","cuisine":"sushi"},{"name":"Chuck E. Cheese","lat":33.88064,"lng":-84.47445,"kind":"restaurant","cuisine":"pizza"},{"name":"Zocalo","lat":33.78152,"lng":-84.38109,"kind":"restaurant","cuisine":"mexican"},{"name":"Nellie B's","lat":33.7815,"lng":-84.38093,"kind":"restaurant","cuisine":"chicken"},{"name":"Fuwah Chinese Restaurant","lat":33.73665,"lng":-84.38603,"kind":"restaurant","cuisine":"chinese"},{"name":"La Fonda Latina","lat":33.83168,"lng":-84.38493,"kind":"restaurant","cuisine":"mexican"},{"name":"Grindhouse Burgers","lat":33.86102,"lng":-84.33707,"kind":"restaurant","cuisine":"burger"},{"name":"The Reading Room","lat":33.77518,"lng":-84.29466,"kind":"cafe","cuisine":"coffee shop"},{"name":"Establishment Atlanta","lat":33.78685,"lng":-84.38216,"kind":"restaurant","cuisine":"american"},{"name":"5Church Atlanta","lat":33.78728,"lng":-84.38278,"kind":"restaurant","cuisine":"american"},{"name":"Elise","lat":33.78951,"lng":-84.38569,"kind":"restaurant","cuisine":"italian"},{"name":"Reverence Cuisine & Cocktails","lat":33.78548,"lng":-84.38765,"kind":"restaurant","cuisine":"american"},{"name":"Hankook Taqueria","lat":33.81156,"lng":-84.43165,"kind":"restaurant","cuisine":"mexican"}]}