{"generated_at":"2026-07-18T03:47:41.039Z","city":"mil","source":"OpenStreetMap (tourism=hotel)","count":89,"hotels":[{"name":"Residence Inn","lat":43.03804,"lng":-87.91071},{"name":"Best Western Plus Milwaukee West","lat":43.01842,"lng":-87.9813},{"name":"SpringHill Suites","lat":43.03979,"lng":-87.91562},{"name":"National Hotel","lat":43.02293,"lng":-87.93108},{"name":"Comfort Suites","lat":43.11623,"lng":-88.05872},{"name":"Sleep Inn & Suites","lat":42.92031,"lng":-88.00974},{"name":"MainStay Suites","lat":42.92012,"lng":-88.00997},{"name":"Kimpton Journeyman Hotel","lat":43.03298,"lng":-87.90675},{"name":"The Pfister Hotel","lat":43.03944,"lng":-87.90572},{"name":"Hotel Metro","lat":43.03975,"lng":-87.90631},{"name":"Holiday Inn Express","lat":43.03729,"lng":-87.90549},{"name":"Tru by Hilton","lat":43.03659,"lng":-87.90541},{"name":"Hyatt Regency Milwaukee","lat":43.04091,"lng":-87.91506},{"name":"Drury Plaza Hotel","lat":43.03894,"lng":-87.90877},{"name":"Saint Kate","lat":43.04179,"lng":-87.91078},{"name":"Candlewood Suites","lat":43.18542,"lng":-87.96654},{"name":"The Brewhouse Inn & Suites","lat":43.04607,"lng":-87.92481},{"name":"Hampton Inn & Suites","lat":43.03904,"lng":-87.91262},{"name":"Hilton Garden Inn","lat":43.03781,"lng":-87.90813},{"name":"Homewood Suites","lat":43.03643,"lng":-87.90848},{"name":"Hyatt Place Milwaukee Airport","lat":42.9471,"lng":-87.9138},{"name":"Best Western Plus Milwaukee Airport Hotel & Conference Center","lat":42.95144,"lng":-87.91159},{"name":"Holiday Inn Express & Suites","lat":42.95789,"lng":-87.91856},{"name":"Kinn MKE Guesthouse","lat":43.03768,"lng":-87.9073},{"name":"Milwaukee Marriott Downtown","lat":43.03821,"lng":-87.90685},{"name":"The Knickerbocker on the Lake","lat":43.04603,"lng":-87.8988},{"name":"Dubbel Dutch","lat":43.04205,"lng":-87.90094},{"name":"The Astor Hotel","lat":43.04616,"lng":-87.90034},{"name":"County Clare Inn","lat":43.04665,"lng":-87.89946},{"name":"Courtyard Marriott","lat":43.03775,"lng":-87.91466},{"name":"Hilton Milwaukee City Center","lat":43.03831,"lng":-87.91818},{"name":"Double Tree by Hilton","lat":43.03816,"lng":-87.9194},{"name":"Fairfield Inn & Suites Milwaukee Downtown","lat":43.03904,"lng":-87.91422},{"name":"Aloft Milwaukee Downtown","lat":43.04616,"lng":-87.914},{"name":"Potawatomi Hotel","lat":43.03082,"lng":-87.93402},{"name":"Hampton Inn - Milwaukee Airport","lat":42.93108,"lng":-87.92786},{"name":"The Westin Milwaukee","lat":43.03725,"lng":-87.90199},{"name":"Candlewood Suites - Milwaukee Airport-Oak Creek","lat":42.92762,"lng":-87.92782},{"name":"Days Inn & Suites by Wyndham Milwaukee","lat":43.05473,"lng":-87.91812},{"name":"Hyatt Place","lat":43.04618,"lng":-87.92159},{"name":"Hilton Garden Inn","lat":42.93703,"lng":-87.90766},{"name":"Home2 Suites by Hilton - Milwaukee Airport","lat":42.93769,"lng":-87.90773},{"name":"Courtyard","lat":42.9604,"lng":-87.91593},{"name":"Cambria Hotel","lat":43.03639,"lng":-87.91175},{"name":"Four Points by Sheraton Milwaukee North Shore","lat":43.18014,"lng":-87.95879},{"name":"Holiday Inn Express Milwaukee N-Brown Deer/Mequon","lat":43.1862,"lng":-87.96631},{"name":"Country Inn & Suites by Radisson","lat":43.17847,"lng":-87.97678},{"name":"Hilton Garden Inn","lat":43.15476,"lng":-88.05436},{"name":"Comfort Suites","lat":43.14969,"lng":-88.04619},{"name":"Hampton Inn Milwaukee Northwest","lat":43.11984,"lng":-88.0563},{"name":"La Quinta Inn & Suites Milwaukee Bayshore Area","lat":43.11552,"lng":-87.91733},{"name":"La Quinta Inn","lat":43.10981,"lng":-87.91552},{"name":"Norwood Inn Milwaukee","lat":43.116,"lng":-88.0543},{"name":"Holiday Inn Milwaukee Riverfront Hotel","lat":43.1024,"lng":-87.91586},{"name":"Renaissance Milwaukee West","lat":43.06066,"lng":-88.04681},{"name":"Radisson Hotel Milwaukee West","lat":43.06029,"lng":-88.04871},{"name":"Homewood Suites by Hilton Wauwatosa Milwaukee","lat":43.07671,"lng":-88.05528},{"name":"Holiday Inn Express Milwaukee","lat":43.0587,"lng":-88.0516},{"name":"Extended Stay America","lat":43.05758,"lng":-88.05051},{"name":"Sonesta Milwaukee West Wauwatosa","lat":43.04468,"lng":-88.04615},{"name":"Residence Inn Milwaukee West","lat":43.04753,"lng":-88.03063},{"name":"Biller Hotel","lat":43.03949,"lng":-87.94083},{"name":"Ambassador Hotel","lat":43.03909,"lng":-87.94191},{"name":"Ambassador Inn at Marquette","lat":43.03832,"lng":-87.94183},{"name":"Village Inn","lat":43.03827,"lng":-87.95195},{"name":"National Avenue Hotel","lat":43.02332,"lng":-87.93442},{"name":"The Iron Horse Hotel","lat":43.02761,"lng":-87.91725},{"name":"Hampton Inn & Suites Milwaukee West","lat":43.01596,"lng":-88.0146},{"name":"Days Inn by Wyndham West Allis/Milwaukee","lat":43.01212,"lng":-88.04796},{"name":"Quality Inn & Suites","lat":42.9642,"lng":-87.94778},{"name":"Travelodge","lat":42.95994,"lng":-87.93663},{"name":"Sleep Inn & Suites Airport","lat":42.96091,"lng":-87.91905},{"name":"Clarion Pointe","lat":42.95255,"lng":-87.9107},{"name":"Country Inn & Suites","lat":42.93176,"lng":-87.92895},{"name":"MainStay Suites - Milwaukee Airport","lat":42.92961,"lng":-87.92739},{"name":"Days Inn & Suites Milwaukee Airport","lat":42.9292,"lng":-87.9313},{"name":"Comfort Suites - Milwaukee Airport","lat":42.92825,"lng":-87.92936},{"name":"Fairfield Inn & Suites - Milwaukee Airport","lat":42.92699,"lng":-87.92855},{"name":"Holiday Inn Express & Suites - Milwaukee Airport","lat":42.92557,"lng":-87.9315},{"name":"Red Roof Inn","lat":42.92904,"lng":-87.92891},{"name":"Home2 Suites by Hilton","lat":43.03693,"lng":-87.90545},{"name":"SpringHill Suites","lat":43.04489,"lng":-88.04273},{"name":"Fairfield Inn & Suites Milwaukee North","lat":43.14548,"lng":-87.91473},{"name":"Residence Inn Milwaukee North/Glendale","lat":43.14454,"lng":-87.91441},{"name":"Hampton Inn","lat":43.14571,"lng":-87.91425},{"name":"Fairfield Inn","lat":43.02005,"lng":-87.96739},{"name":"The Trade, Autograph Collection","lat":43.04595,"lng":-87.91668},{"name":"WoodSpring Suites Milwaukee - Menomonee Falls","lat":43.1618,"lng":-88.06337},{"name":"Home2 Suites","lat":43.0192,"lng":-87.99964}]}